{
  "summary_stats": {
    "read_bandwidth_Bps": 86515361,
    "write_bandwidth_Bps": 43500235,
    "total_bandwidth_Bps": 130015596,
    "max_internal_bandwidth_Bps": 640000000000,
    "max_link_bandwidth_Bps": 480000000000,
    "bandwidth_utilization_perc": 0.020314936875,
    "read_latency_avg_cycles": 84.403643,
    "read_latency_ns_avg": 67.522914,
    "queueing_latency_avg_cycles": 8.057005,
    "queueing_latency_ns_avg": 6.445604,
    "row_hits": 1280242,
    "row_misses": 1656296,
    "row_conflicts": 41622,
    "row_hit_rate_perc": 42.98768367045424,
    "row_miss_rate_perc": 55.6147419883418,
    "row_conflict_rate_perc": 1.397574341203965,
    "avg_req_queue_length": 0.03151,
    "total_active_cycles_rw": 139429180,
    "dram_cycles_simulated": 7329976000,
    "dram_capacity_bytes": 4294967296,
    "channel_0_busy_cycles_includes_refresh": 156577144,
    "read_requests_total": 1981736,
    "write_requests_total": 996424
  },
  "all_metrics": {
    "ramulator.active_cycles_0": 6336544,
    "ramulator.busy_cycles_0": 156577144,
    "ramulator.serving_requests_0": 6502545,
    "ramulator.average_serving_requests_0": 0.000887,
    "ramulator.active_cycles_0_0": 1601062,
    "ramulator.busy_cycles_0_0": 1601062,
    "ramulator.serving_requests_0_0": 1622927,
    "ramulator.average_serving_requests_0_0": 0.000221,
    "ramulator.active_cycles_0_0_0": 800319,
    "ramulator.busy_cycles_0_0_0": 800319,
    "ramulator.serving_requests_0_0_0": 810115,
    "ramulator.average_serving_requests_0_0_0": 0.000111,
    "ramulator.active_cycles_0_0_1": 802597,
    "ramulator.busy_cycles_0_0_1": 802597,
    "ramulator.serving_requests_0_0_1": 812812,
    "ramulator.average_serving_requests_0_0_1": 0.000111,
    "ramulator.active_cycles_0_1": 1610479,
    "ramulator.busy_cycles_0_1": 1610479,
    "ramulator.serving_requests_0_1": 1633664,
    "ramulator.average_serving_requests_0_1": 0.000223,
    "ramulator.active_cycles_0_1_0": 807927,
    "ramulator.busy_cycles_0_1_0": 807927,
    "ramulator.serving_requests_0_1_0": 817864,
    "ramulator.average_serving_requests_0_1_0": 0.000112,
    "ramulator.active_cycles_0_1_1": 804299,
    "ramulator.busy_cycles_0_1_1": 804299,
    "ramulator.serving_requests_0_1_1": 815800,
    "ramulator.average_serving_requests_0_1_1": 0.000111,
    "ramulator.active_cycles_0_2": 1598829,
    "ramulator.busy_cycles_0_2": 1598829,
    "ramulator.serving_requests_0_2": 1624291,
    "ramulator.average_serving_requests_0_2": 0.000222,
    "ramulator.active_cycles_0_2_0": 800191,
    "ramulator.busy_cycles_0_2_0": 800191,
    "ramulator.serving_requests_0_2_0": 810023,
    "ramulator.average_serving_requests_0_2_0": 0.000111,
    "ramulator.active_cycles_0_2_1": 800340,
    "ramulator.busy_cycles_0_2_1": 800340,
    "ramulator.serving_requests_0_2_1": 814268,
    "ramulator.average_serving_requests_0_2_1": 0.000111,
    "ramulator.active_cycles_0_3": 1600017,
    "ramulator.busy_cycles_0_3": 1600017,
    "ramulator.serving_requests_0_3": 1621663,
    "ramulator.average_serving_requests_0_3": 0.000221,
    "ramulator.active_cycles_0_3_0": 794025,
    "ramulator.busy_cycles_0_3_0": 794025,
    "ramulator.serving_requests_0_3_0": 803722,
    "ramulator.average_serving_requests_0_3_0": 0.00011,
    "ramulator.active_cycles_0_3_1": 807857,
    "ramulator.busy_cycles_0_3_1": 807857,
    "ramulator.serving_requests_0_3_1": 817941,
    "ramulator.average_serving_requests_0_3_1": 0.000112,
    "ramulator.active_cycles_1": 6337614,
    "ramulator.busy_cycles_1": 156581214,
    "ramulator.serving_requests_1": 6520153,
    "ramulator.average_serving_requests_1": 0.00089,
    "ramulator.active_cycles_1_0": 1609186,
    "ramulator.busy_cycles_1_0": 1609186,
    "ramulator.serving_requests_1_0": 1629637,
    "ramulator.average_serving_requests_1_0": 0.000222,
    "ramulator.active_cycles_1_0_0": 807777,
    "ramulator.busy_cycles_1_0_0": 807777,
    "ramulator.serving_requests_1_0_0": 817588,
    "ramulator.average_serving_requests_1_0_0": 0.000112,
    "ramulator.active_cycles_1_0_1": 803040,
    "ramulator.busy_cycles_1_0_1": 803040,
    "ramulator.serving_requests_1_0_1": 812049,
    "ramulator.average_serving_requests_1_0_1": 0.000111,
    "ramulator.active_cycles_1_1": 1611518,
    "ramulator.busy_cycles_1_1": 1611518,
    "ramulator.serving_requests_1_1": 1636294,
    "ramulator.average_serving_requests_1_1": 0.000223,
    "ramulator.active_cycles_1_1_0": 807709,
    "ramulator.busy_cycles_1_1_0": 807709,
    "ramulator.serving_requests_1_1_0": 818192,
    "ramulator.average_serving_requests_1_1_0": 0.000112,
    "ramulator.active_cycles_1_1_1": 806249,
    "ramulator.busy_cycles_1_1_1": 806249,
    "ramulator.serving_requests_1_1_1": 818102,
    "ramulator.average_serving_requests_1_1_1": 0.000112,
    "ramulator.active_cycles_1_2": 1607983,
    "ramulator.busy_cycles_1_2": 1607983,
    "ramulator.serving_requests_1_2": 1633749,
    "ramulator.average_serving_requests_1_2": 0.000223,
    "ramulator.active_cycles_1_2_0": 806746,
    "ramulator.busy_cycles_1_2_0": 806746,
    "ramulator.serving_requests_1_2_0": 817330,
    "ramulator.average_serving_requests_1_2_0": 0.000112,
    "ramulator.active_cycles_1_2_1": 803211,
    "ramulator.busy_cycles_1_2_1": 803211,
    "ramulator.serving_requests_1_2_1": 816419,
    "ramulator.average_serving_requests_1_2_1": 0.000111,
    "ramulator.active_cycles_1_3": 1597595,
    "ramulator.busy_cycles_1_3": 1597595,
    "ramulator.serving_requests_1_3": 1620473,
    "ramulator.average_serving_requests_1_3": 0.000221,
    "ramulator.active_cycles_1_3_0": 798786,
    "ramulator.busy_cycles_1_3_0": 798786,
    "ramulator.serving_requests_1_3_0": 808151,
    "ramulator.average_serving_requests_1_3_0": 0.00011,
    "ramulator.active_cycles_1_3_1": 801323,
    "ramulator.busy_cycles_1_3_1": 801323,
    "ramulator.serving_requests_1_3_1": 812322,
    "ramulator.average_serving_requests_1_3_1": 0.000111,
    "ramulator.active_cycles_2": 6330526,
    "ramulator.busy_cycles_2": 156580326,
    "ramulator.serving_requests_2": 6505377,
    "ramulator.average_serving_requests_2": 0.000888,
    "ramulator.active_cycles_2_0": 1603782,
    "ramulator.busy_cycles_2_0": 1603782,
    "ramulator.serving_requests_2_0": 1624822,
    "ramulator.average_serving_requests_2_0": 0.000222,
    "ramulator.active_cycles_2_0_0": 804557,
    "ramulator.busy_cycles_2_0_0": 804557,
    "ramulator.serving_requests_2_0_0": 814606,
    "ramulator.average_serving_requests_2_0_0": 0.000111,
    "ramulator.active_cycles_2_0_1": 800806,
    "ramulator.busy_cycles_2_0_1": 800806,
    "ramulator.serving_requests_2_0_1": 810216,
    "ramulator.average_serving_requests_2_0_1": 0.000111,
    "ramulator.active_cycles_2_1": 1607542,
    "ramulator.busy_cycles_2_1": 1607542,
    "ramulator.serving_requests_2_1": 1631676,
    "ramulator.average_serving_requests_2_1": 0.000223,
    "ramulator.active_cycles_2_1_0": 806066,
    "ramulator.busy_cycles_2_1_0": 806066,
    "ramulator.serving_requests_2_1_0": 815662,
    "ramulator.average_serving_requests_2_1_0": 0.000111,
    "ramulator.active_cycles_2_1_1": 803622,
    "ramulator.busy_cycles_2_1_1": 803622,
    "ramulator.serving_requests_2_1_1": 816014,
    "ramulator.average_serving_requests_2_1_1": 0.000111,
    "ramulator.active_cycles_2_2": 1604646,
    "ramulator.busy_cycles_2_2": 1604646,
    "ramulator.serving_requests_2_2": 1631308,
    "ramulator.average_serving_requests_2_2": 0.000223,
    "ramulator.active_cycles_2_2_0": 801256,
    "ramulator.busy_cycles_2_2_0": 801256,
    "ramulator.serving_requests_2_2_0": 812610,
    "ramulator.average_serving_requests_2_2_0": 0.000111,
    "ramulator.active_cycles_2_2_1": 805492,
    "ramulator.busy_cycles_2_2_1": 805492,
    "ramulator.serving_requests_2_2_1": 818698,
    "ramulator.average_serving_requests_2_2_1": 0.000112,
    "ramulator.active_cycles_2_3": 1595453,
    "ramulator.busy_cycles_2_3": 1595453,
    "ramulator.serving_requests_2_3": 1617571,
    "ramulator.average_serving_requests_2_3": 0.000221,
    "ramulator.active_cycles_2_3_0": 796371,
    "ramulator.busy_cycles_2_3_0": 796371,
    "ramulator.serving_requests_2_3_0": 805914,
    "ramulator.average_serving_requests_2_3_0": 0.00011,
    "ramulator.active_cycles_2_3_1": 801059,
    "ramulator.busy_cycles_2_3_1": 801059,
    "ramulator.serving_requests_2_3_1": 811657,
    "ramulator.average_serving_requests_2_3_1": 0.000111,
    "ramulator.active_cycles_3": 6342517,
    "ramulator.busy_cycles_3": 156579517,
    "ramulator.serving_requests_3": 6515805,
    "ramulator.average_serving_requests_3": 0.000889,
    "ramulator.active_cycles_3_0": 1606115,
    "ramulator.busy_cycles_3_0": 1606115,
    "ramulator.serving_requests_3_0": 1627783,
    "ramulator.average_serving_requests_3_0": 0.000222,
    "ramulator.active_cycles_3_0_0": 803438,
    "ramulator.busy_cycles_3_0_0": 803438,
    "ramulator.serving_requests_3_0_0": 813485,
    "ramulator.average_serving_requests_3_0_0": 0.000111,
    "ramulator.active_cycles_3_0_1": 804496,
    "ramulator.busy_cycles_3_0_1": 804496,
    "ramulator.serving_requests_3_0_1": 814298,
    "ramulator.average_serving_requests_3_0_1": 0.000111,
    "ramulator.active_cycles_3_1": 1607853,
    "ramulator.busy_cycles_3_1": 1607853,
    "ramulator.serving_requests_3_1": 1632025,
    "ramulator.average_serving_requests_3_1": 0.000223,
    "ramulator.active_cycles_3_1_0": 803977,
    "ramulator.busy_cycles_3_1_0": 803977,
    "ramulator.serving_requests_3_1_0": 812777,
    "ramulator.average_serving_requests_3_1_0": 0.000111,
    "ramulator.active_cycles_3_1_1": 806066,
    "ramulator.busy_cycles_3_1_1": 806066,
    "ramulator.serving_requests_3_1_1": 819248,
    "ramulator.average_serving_requests_3_1_1": 0.000112,
    "ramulator.active_cycles_3_2": 1612051,
    "ramulator.busy_cycles_3_2": 1612051,
    "ramulator.serving_requests_3_2": 1638012,
    "ramulator.average_serving_requests_3_2": 0.000223,
    "ramulator.active_cycles_3_2_0": 803747,
    "ramulator.busy_cycles_3_2_0": 803747,
    "ramulator.serving_requests_3_2_0": 813795,
    "ramulator.average_serving_requests_3_2_0": 0.000111,
    "ramulator.active_cycles_3_2_1": 810506,
    "ramulator.busy_cycles_3_2_1": 810506,
    "ramulator.serving_requests_3_2_1": 824217,
    "ramulator.average_serving_requests_3_2_1": 0.000112,
    "ramulator.active_cycles_3_3": 1594725,
    "ramulator.busy_cycles_3_3": 1594725,
    "ramulator.serving_requests_3_3": 1617985,
    "ramulator.average_serving_requests_3_3": 0.000221,
    "ramulator.active_cycles_3_3_0": 798144,
    "ramulator.busy_cycles_3_3_0": 798144,
    "ramulator.serving_requests_3_3_0": 807876,
    "ramulator.average_serving_requests_3_3_0": 0.00011,
    "ramulator.active_cycles_3_3_1": 799163,
    "ramulator.busy_cycles_3_3_1": 799163,
    "ramulator.serving_requests_3_3_1": 810109,
    "ramulator.average_serving_requests_3_3_1": 0.000111,
    "ramulator.active_cycles_4": 6339891,
    "ramulator.busy_cycles_4": 156577491,
    "ramulator.serving_requests_4": 6501295,
    "ramulator.average_serving_requests_4": 0.000887,
    "ramulator.active_cycles_4_0": 1605478,
    "ramulator.busy_cycles_4_0": 1605478,
    "ramulator.serving_requests_4_0": 1626195,
    "ramulator.average_serving_requests_4_0": 0.000222,
    "ramulator.active_cycles_4_0_0": 801328,
    "ramulator.busy_cycles_4_0_0": 801328,
    "ramulator.serving_requests_4_0_0": 810273,
    "ramulator.average_serving_requests_4_0_0": 0.000111,
    "ramulator.active_cycles_4_0_1": 805939,
    "ramulator.busy_cycles_4_0_1": 805939,
    "ramulator.serving_requests_4_0_1": 815922,
    "ramulator.average_serving_requests_4_0_1": 0.000111,
    "ramulator.active_cycles_4_1": 1606994,
    "ramulator.busy_cycles_4_1": 1606994,
    "ramulator.serving_requests_4_1": 1628648,
    "ramulator.average_serving_requests_4_1": 0.000222,
    "ramulator.active_cycles_4_1_0": 804460,
    "ramulator.busy_cycles_4_1_0": 804460,
    "ramulator.serving_requests_4_1_0": 813274,
    "ramulator.average_serving_requests_4_1_0": 0.000111,
    "ramulator.active_cycles_4_1_1": 803801,
    "ramulator.busy_cycles_4_1_1": 803801,
    "ramulator.serving_requests_4_1_1": 815374,
    "ramulator.average_serving_requests_4_1_1": 0.000111,
    "ramulator.active_cycles_4_2": 1604735,
    "ramulator.busy_cycles_4_2": 1604735,
    "ramulator.serving_requests_4_2": 1628532,
    "ramulator.average_serving_requests_4_2": 0.000222,
    "ramulator.active_cycles_4_2_0": 800743,
    "ramulator.busy_cycles_4_2_0": 800743,
    "ramulator.serving_requests_4_2_0": 811196,
    "ramulator.average_serving_requests_4_2_0": 0.000111,
    "ramulator.active_cycles_4_2_1": 806546,
    "ramulator.busy_cycles_4_2_1": 806546,
    "ramulator.serving_requests_4_2_1": 817336,
    "ramulator.average_serving_requests_4_2_1": 0.000112,
    "ramulator.active_cycles_4_3": 1596299,
    "ramulator.busy_cycles_4_3": 1596299,
    "ramulator.serving_requests_4_3": 1617920,
    "ramulator.average_serving_requests_4_3": 0.000221,
    "ramulator.active_cycles_4_3_0": 795894,
    "ramulator.busy_cycles_4_3_0": 795894,
    "ramulator.serving_requests_4_3_0": 806768,
    "ramulator.average_serving_requests_4_3_0": 0.00011,
    "ramulator.active_cycles_4_3_1": 801220,
    "ramulator.busy_cycles_4_3_1": 801220,
    "ramulator.serving_requests_4_3_1": 811152,
    "ramulator.average_serving_requests_4_3_1": 0.000111,
    "ramulator.active_cycles_5": 6327561,
    "ramulator.busy_cycles_5": 156572761,
    "ramulator.serving_requests_5": 6509612,
    "ramulator.average_serving_requests_5": 0.000888,
    "ramulator.active_cycles_5_0": 1608722,
    "ramulator.busy_cycles_5_0": 1608722,
    "ramulator.serving_requests_5_0": 1629594,
    "ramulator.average_serving_requests_5_0": 0.000222,
    "ramulator.active_cycles_5_0_0": 804432,
    "ramulator.busy_cycles_5_0_0": 804432,
    "ramulator.serving_requests_5_0_0": 813078,
    "ramulator.average_serving_requests_5_0_0": 0.000111,
    "ramulator.active_cycles_5_0_1": 806439,
    "ramulator.busy_cycles_5_0_1": 806439,
    "ramulator.serving_requests_5_0_1": 816516,
    "ramulator.average_serving_requests_5_0_1": 0.000111,
    "ramulator.active_cycles_5_1": 1609058,
    "ramulator.busy_cycles_5_1": 1609058,
    "ramulator.serving_requests_5_1": 1630408,
    "ramulator.average_serving_requests_5_1": 0.000222,
    "ramulator.active_cycles_5_1_0": 804070,
    "ramulator.busy_cycles_5_1_0": 804070,
    "ramulator.serving_requests_5_1_0": 812911,
    "ramulator.average_serving_requests_5_1_0": 0.000111,
    "ramulator.active_cycles_5_1_1": 806217,
    "ramulator.busy_cycles_5_1_1": 806217,
    "ramulator.serving_requests_5_1_1": 817497,
    "ramulator.average_serving_requests_5_1_1": 0.000112,
    "ramulator.active_cycles_5_2": 1606830,
    "ramulator.busy_cycles_5_2": 1606830,
    "ramulator.serving_requests_5_2": 1629684,
    "ramulator.average_serving_requests_5_2": 0.000222,
    "ramulator.active_cycles_5_2_0": 802584,
    "ramulator.busy_cycles_5_2_0": 802584,
    "ramulator.serving_requests_5_2_0": 812090,
    "ramulator.average_serving_requests_5_2_0": 0.000111,
    "ramulator.active_cycles_5_2_1": 807276,
    "ramulator.busy_cycles_5_2_1": 807276,
    "ramulator.serving_requests_5_2_1": 817594,
    "ramulator.average_serving_requests_5_2_1": 0.000112,
    "ramulator.active_cycles_5_3": 1598217,
    "ramulator.busy_cycles_5_3": 1598217,
    "ramulator.serving_requests_5_3": 1619926,
    "ramulator.average_serving_requests_5_3": 0.000221,
    "ramulator.active_cycles_5_3_0": 798155,
    "ramulator.busy_cycles_5_3_0": 798155,
    "ramulator.serving_requests_5_3_0": 808295,
    "ramulator.average_serving_requests_5_3_0": 0.00011,
    "ramulator.active_cycles_5_3_1": 801338,
    "ramulator.busy_cycles_5_3_1": 801338,
    "ramulator.serving_requests_5_3_1": 811631,
    "ramulator.average_serving_requests_5_3_1": 0.000111,
    "ramulator.active_cycles_6": 6326082,
    "ramulator.busy_cycles_6": 156572282,
    "ramulator.serving_requests_6": 6493586,
    "ramulator.average_serving_requests_6": 0.000886,
    "ramulator.active_cycles_6_0": 1610356,
    "ramulator.busy_cycles_6_0": 1610356,
    "ramulator.serving_requests_6_0": 1631277,
    "ramulator.average_serving_requests_6_0": 0.000223,
    "ramulator.active_cycles_6_0_0": 807433,
    "ramulator.busy_cycles_6_0_0": 807433,
    "ramulator.serving_requests_6_0_0": 816432,
    "ramulator.average_serving_requests_6_0_0": 0.000111,
    "ramulator.active_cycles_6_0_1": 805497,
    "ramulator.busy_cycles_6_0_1": 805497,
    "ramulator.serving_requests_6_0_1": 814845,
    "ramulator.average_serving_requests_6_0_1": 0.000111,
    "ramulator.active_cycles_6_1": 1603325,
    "ramulator.busy_cycles_6_1": 1603325,
    "ramulator.serving_requests_6_1": 1625188,
    "ramulator.average_serving_requests_6_1": 0.000222,
    "ramulator.active_cycles_6_1_0": 802868,
    "ramulator.busy_cycles_6_1_0": 802868,
    "ramulator.serving_requests_6_1_0": 812157,
    "ramulator.average_serving_requests_6_1_0": 0.000111,
    "ramulator.active_cycles_6_1_1": 801953,
    "ramulator.busy_cycles_6_1_1": 801953,
    "ramulator.serving_requests_6_1_1": 813031,
    "ramulator.average_serving_requests_6_1_1": 0.000111,
    "ramulator.active_cycles_6_2": 1602205,
    "ramulator.busy_cycles_6_2": 1602205,
    "ramulator.serving_requests_6_2": 1624567,
    "ramulator.average_serving_requests_6_2": 0.000222,
    "ramulator.active_cycles_6_2_0": 801836,
    "ramulator.busy_cycles_6_2_0": 801836,
    "ramulator.serving_requests_6_2_0": 810954,
    "ramulator.average_serving_requests_6_2_0": 0.000111,
    "ramulator.active_cycles_6_2_1": 802742,
    "ramulator.busy_cycles_6_2_1": 802742,
    "ramulator.serving_requests_6_2_1": 813613,
    "ramulator.average_serving_requests_6_2_1": 0.000111,
    "ramulator.active_cycles_6_3": 1591305,
    "ramulator.busy_cycles_6_3": 1591305,
    "ramulator.serving_requests_6_3": 1612554,
    "ramulator.average_serving_requests_6_3": 0.00022,
    "ramulator.active_cycles_6_3_0": 797613,
    "ramulator.busy_cycles_6_3_0": 797613,
    "ramulator.serving_requests_6_3_0": 808213,
    "ramulator.average_serving_requests_6_3_0": 0.00011,
    "ramulator.active_cycles_6_3_1": 794751,
    "ramulator.busy_cycles_6_3_1": 794751,
    "ramulator.serving_requests_6_3_1": 804341,
    "ramulator.average_serving_requests_6_3_1": 0.00011,
    "ramulator.active_cycles_7": 6338490,
    "ramulator.busy_cycles_7": 156576890,
    "ramulator.serving_requests_7": 6502178,
    "ramulator.average_serving_requests_7": 0.000887,
    "ramulator.active_cycles_7_0": 1613160,
    "ramulator.busy_cycles_7_0": 1613160,
    "ramulator.serving_requests_7_0": 1633493,
    "ramulator.average_serving_requests_7_0": 0.000223,
    "ramulator.active_cycles_7_0_0": 804479,
    "ramulator.busy_cycles_7_0_0": 804479,
    "ramulator.serving_requests_7_0_0": 813266,
    "ramulator.average_serving_requests_7_0_0": 0.000111,
    "ramulator.active_cycles_7_0_1": 810930,
    "ramulator.busy_cycles_7_0_1": 810930,
    "ramulator.serving_requests_7_0_1": 820227,
    "ramulator.average_serving_requests_7_0_1": 0.000112,
    "ramulator.active_cycles_7_1": 1606011,
    "ramulator.busy_cycles_7_1": 1606011,
    "ramulator.serving_requests_7_1": 1628894,
    "ramulator.average_serving_requests_7_1": 0.000222,
    "ramulator.active_cycles_7_1_0": 805419,
    "ramulator.busy_cycles_7_1_0": 805419,
    "ramulator.serving_requests_7_1_0": 814594,
    "ramulator.average_serving_requests_7_1_0": 0.000111,
    "ramulator.active_cycles_7_1_1": 802087,
    "ramulator.busy_cycles_7_1_1": 802087,
    "ramulator.serving_requests_7_1_1": 814300,
    "ramulator.average_serving_requests_7_1_1": 0.000111,
    "ramulator.active_cycles_7_2": 1602594,
    "ramulator.busy_cycles_7_2": 1602594,
    "ramulator.serving_requests_7_2": 1624253,
    "ramulator.average_serving_requests_7_2": 0.000222,
    "ramulator.active_cycles_7_2_0": 801814,
    "ramulator.busy_cycles_7_2_0": 801814,
    "ramulator.serving_requests_7_2_0": 810792,
    "ramulator.average_serving_requests_7_2_0": 0.000111,
    "ramulator.active_cycles_7_2_1": 802960,
    "ramulator.busy_cycles_7_2_1": 802960,
    "ramulator.serving_requests_7_2_1": 813461,
    "ramulator.average_serving_requests_7_2_1": 0.000111,
    "ramulator.active_cycles_7_3": 1594718,
    "ramulator.busy_cycles_7_3": 1594718,
    "ramulator.serving_requests_7_3": 1615538,
    "ramulator.average_serving_requests_7_3": 0.00022,
    "ramulator.active_cycles_7_3_0": 796349,
    "ramulator.busy_cycles_7_3_0": 796349,
    "ramulator.serving_requests_7_3_0": 805795,
    "ramulator.average_serving_requests_7_3_0": 0.00011,
    "ramulator.active_cycles_7_3_1": 800384,
    "ramulator.busy_cycles_7_3_1": 800384,
    "ramulator.serving_requests_7_3_1": 809743,
    "ramulator.average_serving_requests_7_3_1": 0.00011,
    "ramulator.active_cycles_8": 6339950,
    "ramulator.busy_cycles_8": 156581550,
    "ramulator.serving_requests_8": 6500331,
    "ramulator.average_serving_requests_8": 0.000887,
    "ramulator.active_cycles_8_0": 1610371,
    "ramulator.busy_cycles_8_0": 1610371,
    "ramulator.serving_requests_8_0": 1631048,
    "ramulator.average_serving_requests_8_0": 0.000223,
    "ramulator.active_cycles_8_0_0": 803605,
    "ramulator.busy_cycles_8_0_0": 803605,
    "ramulator.serving_requests_8_0_0": 813969,
    "ramulator.average_serving_requests_8_0_0": 0.000111,
    "ramulator.active_cycles_8_0_1": 808028,
    "ramulator.busy_cycles_8_0_1": 808028,
    "ramulator.serving_requests_8_0_1": 817079,
    "ramulator.average_serving_requests_8_0_1": 0.000111,
    "ramulator.active_cycles_8_1": 1603137,
    "ramulator.busy_cycles_8_1": 1603137,
    "ramulator.serving_requests_8_1": 1623956,
    "ramulator.average_serving_requests_8_1": 0.000222,
    "ramulator.active_cycles_8_1_0": 803311,
    "ramulator.busy_cycles_8_1_0": 803311,
    "ramulator.serving_requests_8_1_0": 812898,
    "ramulator.average_serving_requests_8_1_0": 0.000111,
    "ramulator.active_cycles_8_1_1": 801328,
    "ramulator.busy_cycles_8_1_1": 801328,
    "ramulator.serving_requests_8_1_1": 811058,
    "ramulator.average_serving_requests_8_1_1": 0.000111,
    "ramulator.active_cycles_8_2": 1604104,
    "ramulator.busy_cycles_8_2": 1604104,
    "ramulator.serving_requests_8_2": 1626580,
    "ramulator.average_serving_requests_8_2": 0.000222,
    "ramulator.active_cycles_8_2_0": 802654,
    "ramulator.busy_cycles_8_2_0": 802654,
    "ramulator.serving_requests_8_2_0": 811798,
    "ramulator.average_serving_requests_8_2_0": 0.000111,
    "ramulator.active_cycles_8_2_1": 804042,
    "ramulator.busy_cycles_8_2_1": 804042,
    "ramulator.serving_requests_8_2_1": 814782,
    "ramulator.average_serving_requests_8_2_1": 0.000111,
    "ramulator.active_cycles_8_3": 1597644,
    "ramulator.busy_cycles_8_3": 1597644,
    "ramulator.serving_requests_8_3": 1618747,
    "ramulator.average_serving_requests_8_3": 0.000221,
    "ramulator.active_cycles_8_3_0": 801465,
    "ramulator.busy_cycles_8_3_0": 801465,
    "ramulator.serving_requests_8_3_0": 811445,
    "ramulator.average_serving_requests_8_3_0": 0.000111,
    "ramulator.active_cycles_8_3_1": 798297,
    "ramulator.busy_cycles_8_3_1": 798297,
    "ramulator.serving_requests_8_3_1": 807302,
    "ramulator.average_serving_requests_8_3_1": 0.00011,
    "ramulator.active_cycles_9": 6333867,
    "ramulator.busy_cycles_9": 156579867,
    "ramulator.serving_requests_9": 6507720,
    "ramulator.average_serving_requests_9": 0.000888,
    "ramulator.active_cycles_9_0": 1610894,
    "ramulator.busy_cycles_9_0": 1610894,
    "ramulator.serving_requests_9_0": 1631570,
    "ramulator.average_serving_requests_9_0": 0.000223,
    "ramulator.active_cycles_9_0_0": 805090,
    "ramulator.busy_cycles_9_0_0": 805090,
    "ramulator.serving_requests_9_0_0": 816017,
    "ramulator.average_serving_requests_9_0_0": 0.000111,
    "ramulator.active_cycles_9_0_1": 806758,
    "ramulator.busy_cycles_9_0_1": 806758,
    "ramulator.serving_requests_9_0_1": 815553,
    "ramulator.average_serving_requests_9_0_1": 0.000111,
    "ramulator.active_cycles_9_1": 1611392,
    "ramulator.busy_cycles_9_1": 1611392,
    "ramulator.serving_requests_9_1": 1631899,
    "ramulator.average_serving_requests_9_1": 0.000223,
    "ramulator.active_cycles_9_1_0": 808207,
    "ramulator.busy_cycles_9_1_0": 808207,
    "ramulator.serving_requests_9_1_0": 816927,
    "ramulator.average_serving_requests_9_1_0": 0.000111,
    "ramulator.active_cycles_9_1_1": 804646,
    "ramulator.busy_cycles_9_1_1": 804646,
    "ramulator.serving_requests_9_1_1": 814972,
    "ramulator.average_serving_requests_9_1_1": 0.000111,
    "ramulator.active_cycles_9_2": 1607416,
    "ramulator.busy_cycles_9_2": 1607416,
    "ramulator.serving_requests_9_2": 1629364,
    "ramulator.average_serving_requests_9_2": 0.000222,
    "ramulator.active_cycles_9_2_0": 806744,
    "ramulator.busy_cycles_9_2_0": 806744,
    "ramulator.serving_requests_9_2_0": 816296,
    "ramulator.average_serving_requests_9_2_0": 0.000111,
    "ramulator.active_cycles_9_2_1": 802786,
    "ramulator.busy_cycles_9_2_1": 802786,
    "ramulator.serving_requests_9_2_1": 813068,
    "ramulator.average_serving_requests_9_2_1": 0.000111,
    "ramulator.active_cycles_9_3": 1592661,
    "ramulator.busy_cycles_9_3": 1592661,
    "ramulator.serving_requests_9_3": 1614887,
    "ramulator.average_serving_requests_9_3": 0.00022,
    "ramulator.active_cycles_9_3_0": 796492,
    "ramulator.busy_cycles_9_3_0": 796492,
    "ramulator.serving_requests_9_3_0": 807876,
    "ramulator.average_serving_requests_9_3_0": 0.00011,
    "ramulator.active_cycles_9_3_1": 797507,
    "ramulator.busy_cycles_9_3_1": 797507,
    "ramulator.serving_requests_9_3_1": 807011,
    "ramulator.average_serving_requests_9_3_1": 0.00011,
    "ramulator.active_cycles_10": 6331463,
    "ramulator.busy_cycles_10": 156578263,
    "ramulator.serving_requests_10": 6492761,
    "ramulator.average_serving_requests_10": 0.000886,
    "ramulator.active_cycles_10_0": 1609284,
    "ramulator.busy_cycles_10_0": 1609284,
    "ramulator.serving_requests_10_0": 1631439,
    "ramulator.average_serving_requests_10_0": 0.000223,
    "ramulator.active_cycles_10_0_0": 806957,
    "ramulator.busy_cycles_10_0_0": 806957,
    "ramulator.serving_requests_10_0_0": 818100,
    "ramulator.average_serving_requests_10_0_0": 0.000112,
    "ramulator.active_cycles_10_0_1": 803478,
    "ramulator.busy_cycles_10_0_1": 803478,
    "ramulator.serving_requests_10_0_1": 813339,
    "ramulator.average_serving_requests_10_0_1": 0.000111,
    "ramulator.active_cycles_10_1": 1604336,
    "ramulator.busy_cycles_10_1": 1604336,
    "ramulator.serving_requests_10_1": 1625928,
    "ramulator.average_serving_requests_10_1": 0.000222,
    "ramulator.active_cycles_10_1_0": 804008,
    "ramulator.busy_cycles_10_1_0": 804008,
    "ramulator.serving_requests_10_1_0": 813607,
    "ramulator.average_serving_requests_10_1_0": 0.000111,
    "ramulator.active_cycles_10_1_1": 801418,
    "ramulator.busy_cycles_10_1_1": 801418,
    "ramulator.serving_requests_10_1_1": 812321,
    "ramulator.average_serving_requests_10_1_1": 0.000111,
    "ramulator.active_cycles_10_2": 1600359,
    "ramulator.busy_cycles_10_2": 1600359,
    "ramulator.serving_requests_10_2": 1622036,
    "ramulator.average_serving_requests_10_2": 0.000221,
    "ramulator.active_cycles_10_2_0": 799279,
    "ramulator.busy_cycles_10_2_0": 799279,
    "ramulator.serving_requests_10_2_0": 809328,
    "ramulator.average_serving_requests_10_2_0": 0.00011,
    "ramulator.active_cycles_10_2_1": 802543,
    "ramulator.busy_cycles_10_2_1": 802543,
    "ramulator.serving_requests_10_2_1": 812708,
    "ramulator.average_serving_requests_10_2_1": 0.000111,
    "ramulator.active_cycles_10_3": 1591265,
    "ramulator.busy_cycles_10_3": 1591265,
    "ramulator.serving_requests_10_3": 1613358,
    "ramulator.average_serving_requests_10_3": 0.00022,
    "ramulator.active_cycles_10_3_0": 798115,
    "ramulator.busy_cycles_10_3_0": 798115,
    "ramulator.serving_requests_10_3_0": 808809,
    "ramulator.average_serving_requests_10_3_0": 0.00011,
    "ramulator.active_cycles_10_3_1": 794203,
    "ramulator.busy_cycles_10_3_1": 794203,
    "ramulator.serving_requests_10_3_1": 804549,
    "ramulator.average_serving_requests_10_3_1": 0.00011,
    "ramulator.active_cycles_11": 6343093,
    "ramulator.busy_cycles_11": 156576693,
    "ramulator.serving_requests_11": 6502830,
    "ramulator.average_serving_requests_11": 0.000887,
    "ramulator.active_cycles_11_0": 1609565,
    "ramulator.busy_cycles_11_0": 1609565,
    "ramulator.serving_requests_11_0": 1632096,
    "ramulator.average_serving_requests_11_0": 0.000223,
    "ramulator.active_cycles_11_0_0": 803569,
    "ramulator.busy_cycles_11_0_0": 803569,
    "ramulator.serving_requests_11_0_0": 814156,
    "ramulator.average_serving_requests_11_0_0": 0.000111,
    "ramulator.active_cycles_11_0_1": 807324,
    "ramulator.busy_cycles_11_0_1": 807324,
    "ramulator.serving_requests_11_0_1": 817940,
    "ramulator.average_serving_requests_11_0_1": 0.000112,
    "ramulator.active_cycles_11_1": 1610115,
    "ramulator.busy_cycles_11_1": 1610115,
    "ramulator.serving_requests_11_1": 1633113,
    "ramulator.average_serving_requests_11_1": 0.000223,
    "ramulator.active_cycles_11_1_0": 808412,
    "ramulator.busy_cycles_11_1_0": 808412,
    "ramulator.serving_requests_11_1_0": 818790,
    "ramulator.average_serving_requests_11_1_0": 0.000112,
    "ramulator.active_cycles_11_1_1": 803227,
    "ramulator.busy_cycles_11_1_1": 803227,
    "ramulator.serving_requests_11_1_1": 814323,
    "ramulator.average_serving_requests_11_1_1": 0.000111,
    "ramulator.active_cycles_11_2": 1601116,
    "ramulator.busy_cycles_11_2": 1601116,
    "ramulator.serving_requests_11_2": 1621951,
    "ramulator.average_serving_requests_11_2": 0.000221,
    "ramulator.active_cycles_11_2_0": 800177,
    "ramulator.busy_cycles_11_2_0": 800177,
    "ramulator.serving_requests_11_2_0": 809464,
    "ramulator.average_serving_requests_11_2_0": 0.00011,
    "ramulator.active_cycles_11_2_1": 802417,
    "ramulator.busy_cycles_11_2_1": 802417,
    "ramulator.serving_requests_11_2_1": 812487,
    "ramulator.average_serving_requests_11_2_1": 0.000111,
    "ramulator.active_cycles_11_3": 1594161,
    "ramulator.busy_cycles_11_3": 1594161,
    "ramulator.serving_requests_11_3": 1615670,
    "ramulator.average_serving_requests_11_3": 0.00022,
    "ramulator.active_cycles_11_3_0": 797554,
    "ramulator.busy_cycles_11_3_0": 797554,
    "ramulator.serving_requests_11_3_0": 807796,
    "ramulator.average_serving_requests_11_3_0": 0.00011,
    "ramulator.active_cycles_11_3_1": 798118,
    "ramulator.busy_cycles_11_3_1": 798118,
    "ramulator.serving_requests_11_3_1": 807874,
    "ramulator.average_serving_requests_11_3_1": 0.00011,
    "ramulator.active_cycles_12": 6336909,
    "ramulator.busy_cycles_12": 156577109,
    "ramulator.serving_requests_12": 6490279,
    "ramulator.average_serving_requests_12": 0.000885,
    "ramulator.active_cycles_12_0": 1607151,
    "ramulator.busy_cycles_12_0": 1607151,
    "ramulator.serving_requests_12_0": 1626777,
    "ramulator.average_serving_requests_12_0": 0.000222,
    "ramulator.active_cycles_12_0_0": 804372,
    "ramulator.busy_cycles_12_0_0": 804372,
    "ramulator.serving_requests_12_0_0": 813558,
    "ramulator.average_serving_requests_12_0_0": 0.000111,
    "ramulator.active_cycles_12_0_1": 803882,
    "ramulator.busy_cycles_12_0_1": 803882,
    "ramulator.serving_requests_12_0_1": 813219,
    "ramulator.average_serving_requests_12_0_1": 0.000111,
    "ramulator.active_cycles_12_1": 1605038,
    "ramulator.busy_cycles_12_1": 1605038,
    "ramulator.serving_requests_12_1": 1626317,
    "ramulator.average_serving_requests_12_1": 0.000222,
    "ramulator.active_cycles_12_1_0": 802493,
    "ramulator.busy_cycles_12_1_0": 802493,
    "ramulator.serving_requests_12_1_0": 812757,
    "ramulator.average_serving_requests_12_1_0": 0.000111,
    "ramulator.active_cycles_12_1_1": 803998,
    "ramulator.busy_cycles_12_1_1": 803998,
    "ramulator.serving_requests_12_1_1": 813560,
    "ramulator.average_serving_requests_12_1_1": 0.000111,
    "ramulator.active_cycles_12_2": 1599395,
    "ramulator.busy_cycles_12_2": 1599395,
    "ramulator.serving_requests_12_2": 1620311,
    "ramulator.average_serving_requests_12_2": 0.000221,
    "ramulator.active_cycles_12_2_0": 803939,
    "ramulator.busy_cycles_12_2_0": 803939,
    "ramulator.serving_requests_12_2_0": 813711,
    "ramulator.average_serving_requests_12_2_0": 0.000111,
    "ramulator.active_cycles_12_2_1": 796979,
    "ramulator.busy_cycles_12_2_1": 796979,
    "ramulator.serving_requests_12_2_1": 806600,
    "ramulator.average_serving_requests_12_2_1": 0.00011,
    "ramulator.active_cycles_12_3": 1594368,
    "ramulator.busy_cycles_12_3": 1594368,
    "ramulator.serving_requests_12_3": 1616874,
    "ramulator.average_serving_requests_12_3": 0.000221,
    "ramulator.active_cycles_12_3_0": 795039,
    "ramulator.busy_cycles_12_3_0": 795039,
    "ramulator.serving_requests_12_3_0": 806145,
    "ramulator.average_serving_requests_12_3_0": 0.00011,
    "ramulator.active_cycles_12_3_1": 800398,
    "ramulator.busy_cycles_12_3_1": 800398,
    "ramulator.serving_requests_12_3_1": 810729,
    "ramulator.average_serving_requests_12_3_1": 0.000111,
    "ramulator.active_cycles_13": 6326744,
    "ramulator.busy_cycles_13": 156573544,
    "ramulator.serving_requests_13": 6501939,
    "ramulator.average_serving_requests_13": 0.000887,
    "ramulator.active_cycles_13_0": 1607624,
    "ramulator.busy_cycles_13_0": 1607624,
    "ramulator.serving_requests_13_0": 1627525,
    "ramulator.average_serving_requests_13_0": 0.000222,
    "ramulator.active_cycles_13_0_0": 802750,
    "ramulator.busy_cycles_13_0_0": 802750,
    "ramulator.serving_requests_13_0_0": 812422,
    "ramulator.average_serving_requests_13_0_0": 0.000111,
    "ramulator.active_cycles_13_0_1": 805963,
    "ramulator.busy_cycles_13_0_1": 805963,
    "ramulator.serving_requests_13_0_1": 815103,
    "ramulator.average_serving_requests_13_0_1": 0.000111,
    "ramulator.active_cycles_13_1": 1606799,
    "ramulator.busy_cycles_13_1": 1606799,
    "ramulator.serving_requests_13_1": 1628633,
    "ramulator.average_serving_requests_13_1": 0.000222,
    "ramulator.active_cycles_13_1_0": 809564,
    "ramulator.busy_cycles_13_1_0": 809564,
    "ramulator.serving_requests_13_1_0": 819912,
    "ramulator.average_serving_requests_13_1_0": 0.000112,
    "ramulator.active_cycles_13_1_1": 799375,
    "ramulator.busy_cycles_13_1_1": 799375,
    "ramulator.serving_requests_13_1_1": 808721,
    "ramulator.average_serving_requests_13_1_1": 0.00011,
    "ramulator.active_cycles_13_2": 1604110,
    "ramulator.busy_cycles_13_2": 1604110,
    "ramulator.serving_requests_13_2": 1625412,
    "ramulator.average_serving_requests_13_2": 0.000222,
    "ramulator.active_cycles_13_2_0": 806201,
    "ramulator.busy_cycles_13_2_0": 806201,
    "ramulator.serving_requests_13_2_0": 816507,
    "ramulator.average_serving_requests_13_2_0": 0.000111,
    "ramulator.active_cycles_13_2_1": 799210,
    "ramulator.busy_cycles_13_2_1": 799210,
    "ramulator.serving_requests_13_2_1": 808905,
    "ramulator.average_serving_requests_13_2_1": 0.00011,
    "ramulator.active_cycles_13_3": 1598553,
    "ramulator.busy_cycles_13_3": 1598553,
    "ramulator.serving_requests_13_3": 1620369,
    "ramulator.average_serving_requests_13_3": 0.000221,
    "ramulator.active_cycles_13_3_0": 800537,
    "ramulator.busy_cycles_13_3_0": 800537,
    "ramulator.serving_requests_13_3_0": 811411,
    "ramulator.average_serving_requests_13_3_0": 0.000111,
    "ramulator.active_cycles_13_3_1": 798964,
    "ramulator.busy_cycles_13_3_1": 798964,
    "ramulator.serving_requests_13_3_1": 808958,
    "ramulator.average_serving_requests_13_3_1": 0.00011,
    "ramulator.active_cycles_14": 6338309,
    "ramulator.busy_cycles_14": 156576509,
    "ramulator.serving_requests_14": 6493295,
    "ramulator.average_serving_requests_14": 0.000886,
    "ramulator.active_cycles_14_0": 1609432,
    "ramulator.busy_cycles_14_0": 1609432,
    "ramulator.serving_requests_14_0": 1628622,
    "ramulator.average_serving_requests_14_0": 0.000222,
    "ramulator.active_cycles_14_0_0": 807017,
    "ramulator.busy_cycles_14_0_0": 807017,
    "ramulator.serving_requests_14_0_0": 815902,
    "ramulator.average_serving_requests_14_0_0": 0.000111,
    "ramulator.active_cycles_14_0_1": 802901,
    "ramulator.busy_cycles_14_0_1": 802901,
    "ramulator.serving_requests_14_0_1": 812720,
    "ramulator.average_serving_requests_14_0_1": 0.000111,
    "ramulator.active_cycles_14_1": 1609489,
    "ramulator.busy_cycles_14_1": 1609489,
    "ramulator.serving_requests_14_1": 1631174,
    "ramulator.average_serving_requests_14_1": 0.000223,
    "ramulator.active_cycles_14_1_0": 804003,
    "ramulator.busy_cycles_14_1_0": 804003,
    "ramulator.serving_requests_14_1_0": 814078,
    "ramulator.average_serving_requests_14_1_0": 0.000111,
    "ramulator.active_cycles_14_1_1": 807284,
    "ramulator.busy_cycles_14_1_1": 807284,
    "ramulator.serving_requests_14_1_1": 817096,
    "ramulator.average_serving_requests_14_1_1": 0.000111,
    "ramulator.active_cycles_14_2": 1596710,
    "ramulator.busy_cycles_14_2": 1596710,
    "ramulator.serving_requests_14_2": 1616376,
    "ramulator.average_serving_requests_14_2": 0.000221,
    "ramulator.active_cycles_14_2_0": 801920,
    "ramulator.busy_cycles_14_2_0": 801920,
    "ramulator.serving_requests_14_2_0": 811511,
    "ramulator.average_serving_requests_14_2_0": 0.000111,
    "ramulator.active_cycles_14_2_1": 796285,
    "ramulator.busy_cycles_14_2_1": 796285,
    "ramulator.serving_requests_14_2_1": 804865,
    "ramulator.average_serving_requests_14_2_1": 0.00011,
    "ramulator.active_cycles_14_3": 1596231,
    "ramulator.busy_cycles_14_3": 1596231,
    "ramulator.serving_requests_14_3": 1617123,
    "ramulator.average_serving_requests_14_3": 0.000221,
    "ramulator.active_cycles_14_3_0": 799999,
    "ramulator.busy_cycles_14_3_0": 799999,
    "ramulator.serving_requests_14_3_0": 809882,
    "ramulator.average_serving_requests_14_3_0": 0.00011,
    "ramulator.active_cycles_14_3_1": 796561,
    "ramulator.busy_cycles_14_3_1": 796561,
    "ramulator.serving_requests_14_3_1": 807241,
    "ramulator.average_serving_requests_14_3_1": 0.00011,
    "ramulator.active_cycles_15": 6325902,
    "ramulator.busy_cycles_15": 156566302,
    "ramulator.serving_requests_15": 6489362,
    "ramulator.average_serving_requests_15": 0.000885,
    "ramulator.active_cycles_15_0": 1604379,
    "ramulator.busy_cycles_15_0": 1604379,
    "ramulator.serving_requests_15_0": 1623691,
    "ramulator.average_serving_requests_15_0": 0.000222,
    "ramulator.active_cycles_15_0_0": 802707,
    "ramulator.busy_cycles_15_0_0": 802707,
    "ramulator.serving_requests_15_0_0": 811898,
    "ramulator.average_serving_requests_15_0_0": 0.000111,
    "ramulator.active_cycles_15_0_1": 802456,
    "ramulator.busy_cycles_15_0_1": 802456,
    "ramulator.serving_requests_15_0_1": 811793,
    "ramulator.average_serving_requests_15_0_1": 0.000111,
    "ramulator.active_cycles_15_1": 1601647,
    "ramulator.busy_cycles_15_1": 1601647,
    "ramulator.serving_requests_15_1": 1624076,
    "ramulator.average_serving_requests_15_1": 0.000222,
    "ramulator.active_cycles_15_1_0": 803675,
    "ramulator.busy_cycles_15_1_0": 803675,
    "ramulator.serving_requests_15_1_0": 814724,
    "ramulator.average_serving_requests_15_1_0": 0.000111,
    "ramulator.active_cycles_15_1_1": 799753,
    "ramulator.busy_cycles_15_1_1": 799753,
    "ramulator.serving_requests_15_1_1": 809352,
    "ramulator.average_serving_requests_15_1_1": 0.00011,
    "ramulator.active_cycles_15_2": 1603241,
    "ramulator.busy_cycles_15_2": 1603241,
    "ramulator.serving_requests_15_2": 1622455,
    "ramulator.average_serving_requests_15_2": 0.000221,
    "ramulator.active_cycles_15_2_0": 803292,
    "ramulator.busy_cycles_15_2_0": 803292,
    "ramulator.serving_requests_15_2_0": 811910,
    "ramulator.average_serving_requests_15_2_0": 0.000111,
    "ramulator.active_cycles_15_2_1": 801827,
    "ramulator.busy_cycles_15_2_1": 801827,
    "ramulator.serving_requests_15_2_1": 810545,
    "ramulator.average_serving_requests_15_2_1": 0.000111,
    "ramulator.active_cycles_15_3": 1598739,
    "ramulator.busy_cycles_15_3": 1598739,
    "ramulator.serving_requests_15_3": 1619140,
    "ramulator.average_serving_requests_15_3": 0.000221,
    "ramulator.active_cycles_15_3_0": 803677,
    "ramulator.busy_cycles_15_3_0": 803677,
    "ramulator.serving_requests_15_3_0": 813873,
    "ramulator.average_serving_requests_15_3_0": 0.000111,
    "ramulator.active_cycles_15_3_1": 795871,
    "ramulator.busy_cycles_15_3_1": 795871,
    "ramulator.serving_requests_15_3_1": 805267,
    "ramulator.average_serving_requests_15_3_1": 0.00011,
    "ramulator.active_cycles_16": 6326409,
    "ramulator.busy_cycles_16": 156572209,
    "ramulator.serving_requests_16": 6480629,
    "ramulator.average_serving_requests_16": 0.000884,
    "ramulator.active_cycles_16_0": 1599550,
    "ramulator.busy_cycles_16_0": 1599550,
    "ramulator.serving_requests_16_0": 1620754,
    "ramulator.average_serving_requests_16_0": 0.000221,
    "ramulator.active_cycles_16_0_0": 803675,
    "ramulator.busy_cycles_16_0_0": 803675,
    "ramulator.serving_requests_16_0_0": 813449,
    "ramulator.average_serving_requests_16_0_0": 0.000111,
    "ramulator.active_cycles_16_0_1": 797722,
    "ramulator.busy_cycles_16_0_1": 797722,
    "ramulator.serving_requests_16_0_1": 807305,
    "ramulator.average_serving_requests_16_0_1": 0.00011,
    "ramulator.active_cycles_16_1": 1599740,
    "ramulator.busy_cycles_16_1": 1599740,
    "ramulator.serving_requests_16_1": 1622666,
    "ramulator.average_serving_requests_16_1": 0.000221,
    "ramulator.active_cycles_16_1_0": 798874,
    "ramulator.busy_cycles_16_1_0": 798874,
    "ramulator.serving_requests_16_1_0": 810130,
    "ramulator.average_serving_requests_16_1_0": 0.000111,
    "ramulator.active_cycles_16_1_1": 801963,
    "ramulator.busy_cycles_16_1_1": 801963,
    "ramulator.serving_requests_16_1_1": 812536,
    "ramulator.average_serving_requests_16_1_1": 0.000111,
    "ramulator.active_cycles_16_2": 1590889,
    "ramulator.busy_cycles_16_2": 1590889,
    "ramulator.serving_requests_16_2": 1611838,
    "ramulator.average_serving_requests_16_2": 0.00022,
    "ramulator.active_cycles_16_2_0": 798020,
    "ramulator.busy_cycles_16_2_0": 798020,
    "ramulator.serving_requests_16_2_0": 807370,
    "ramulator.average_serving_requests_16_2_0": 0.00011,
    "ramulator.active_cycles_16_2_1": 794250,
    "ramulator.busy_cycles_16_2_1": 794250,
    "ramulator.serving_requests_16_2_1": 804468,
    "ramulator.average_serving_requests_16_2_1": 0.00011,
    "ramulator.active_cycles_16_3": 1603979,
    "ramulator.busy_cycles_16_3": 1603979,
    "ramulator.serving_requests_16_3": 1625371,
    "ramulator.average_serving_requests_16_3": 0.000222,
    "ramulator.active_cycles_16_3_0": 805012,
    "ramulator.busy_cycles_16_3_0": 805012,
    "ramulator.serving_requests_16_3_0": 816388,
    "ramulator.average_serving_requests_16_3_0": 0.000111,
    "ramulator.active_cycles_16_3_1": 799235,
    "ramulator.busy_cycles_16_3_1": 799235,
    "ramulator.serving_requests_16_3_1": 808983,
    "ramulator.average_serving_requests_16_3_1": 0.00011,
    "ramulator.active_cycles_17": 6332300,
    "ramulator.busy_cycles_17": 156573300,
    "ramulator.serving_requests_17": 6509155,
    "ramulator.average_serving_requests_17": 0.000888,
    "ramulator.active_cycles_17_0": 1612814,
    "ramulator.busy_cycles_17_0": 1612814,
    "ramulator.serving_requests_17_0": 1633771,
    "ramulator.average_serving_requests_17_0": 0.000223,
    "ramulator.active_cycles_17_0_0": 809199,
    "ramulator.busy_cycles_17_0_0": 809199,
    "ramulator.serving_requests_17_0_0": 818594,
    "ramulator.average_serving_requests_17_0_0": 0.000112,
    "ramulator.active_cycles_17_0_1": 805336,
    "ramulator.busy_cycles_17_0_1": 805336,
    "ramulator.serving_requests_17_0_1": 815177,
    "ramulator.average_serving_requests_17_0_1": 0.000111,
    "ramulator.active_cycles_17_1": 1606798,
    "ramulator.busy_cycles_17_1": 1606798,
    "ramulator.serving_requests_17_1": 1631633,
    "ramulator.average_serving_requests_17_1": 0.000223,
    "ramulator.active_cycles_17_1_0": 802519,
    "ramulator.busy_cycles_17_1_0": 802519,
    "ramulator.serving_requests_17_1_0": 813971,
    "ramulator.average_serving_requests_17_1_0": 0.000111,
    "ramulator.active_cycles_17_1_1": 806112,
    "ramulator.busy_cycles_17_1_1": 806112,
    "ramulator.serving_requests_17_1_1": 817662,
    "ramulator.average_serving_requests_17_1_1": 0.000112,
    "ramulator.active_cycles_17_2": 1598834,
    "ramulator.busy_cycles_17_2": 1598834,
    "ramulator.serving_requests_17_2": 1619376,
    "ramulator.average_serving_requests_17_2": 0.000221,
    "ramulator.active_cycles_17_2_0": 804677,
    "ramulator.busy_cycles_17_2_0": 804677,
    "ramulator.serving_requests_17_2_0": 814205,
    "ramulator.average_serving_requests_17_2_0": 0.000111,
    "ramulator.active_cycles_17_2_1": 795932,
    "ramulator.busy_cycles_17_2_1": 795932,
    "ramulator.serving_requests_17_2_1": 805171,
    "ramulator.average_serving_requests_17_2_1": 0.00011,
    "ramulator.active_cycles_17_3": 1603146,
    "ramulator.busy_cycles_17_3": 1603146,
    "ramulator.serving_requests_17_3": 1624375,
    "ramulator.average_serving_requests_17_3": 0.000222,
    "ramulator.active_cycles_17_3_0": 804424,
    "ramulator.busy_cycles_17_3_0": 804424,
    "ramulator.serving_requests_17_3_0": 815095,
    "ramulator.average_serving_requests_17_3_0": 0.000111,
    "ramulator.active_cycles_17_3_1": 799538,
    "ramulator.busy_cycles_17_3_1": 799538,
    "ramulator.serving_requests_17_3_1": 809280,
    "ramulator.average_serving_requests_17_3_1": 0.00011,
    "ramulator.active_cycles_18": 6328832,
    "ramulator.busy_cycles_18": 156570432,
    "ramulator.serving_requests_18": 6485703,
    "ramulator.average_serving_requests_18": 0.000885,
    "ramulator.active_cycles_18_0": 1606493,
    "ramulator.busy_cycles_18_0": 1606493,
    "ramulator.serving_requests_18_0": 1627526,
    "ramulator.average_serving_requests_18_0": 0.000222,
    "ramulator.active_cycles_18_0_0": 804308,
    "ramulator.busy_cycles_18_0_0": 804308,
    "ramulator.serving_requests_18_0_0": 813838,
    "ramulator.average_serving_requests_18_0_0": 0.000111,
    "ramulator.active_cycles_18_0_1": 803923,
    "ramulator.busy_cycles_18_0_1": 803923,
    "ramulator.serving_requests_18_0_1": 813688,
    "ramulator.average_serving_requests_18_0_1": 0.000111,
    "ramulator.active_cycles_18_1": 1602247,
    "ramulator.busy_cycles_18_1": 1602247,
    "ramulator.serving_requests_18_1": 1625264,
    "ramulator.average_serving_requests_18_1": 0.000222,
    "ramulator.active_cycles_18_1_0": 804956,
    "ramulator.busy_cycles_18_1_0": 804956,
    "ramulator.serving_requests_18_1_0": 815604,
    "ramulator.average_serving_requests_18_1_0": 0.000111,
    "ramulator.active_cycles_18_1_1": 798534,
    "ramulator.busy_cycles_18_1_1": 798534,
    "ramulator.serving_requests_18_1_1": 809660,
    "ramulator.average_serving_requests_18_1_1": 0.00011,
    "ramulator.active_cycles_18_2": 1593922,
    "ramulator.busy_cycles_18_2": 1593922,
    "ramulator.serving_requests_18_2": 1614301,
    "ramulator.average_serving_requests_18_2": 0.00022,
    "ramulator.active_cycles_18_2_0": 801329,
    "ramulator.busy_cycles_18_2_0": 801329,
    "ramulator.serving_requests_18_2_0": 810728,
    "ramulator.average_serving_requests_18_2_0": 0.000111,
    "ramulator.active_cycles_18_2_1": 793250,
    "ramulator.busy_cycles_18_2_1": 793250,
    "ramulator.serving_requests_18_2_1": 803573,
    "ramulator.average_serving_requests_18_2_1": 0.00011,
    "ramulator.active_cycles_18_3": 1597464,
    "ramulator.busy_cycles_18_3": 1597464,
    "ramulator.serving_requests_18_3": 1618612,
    "ramulator.average_serving_requests_18_3": 0.000221,
    "ramulator.active_cycles_18_3_0": 800640,
    "ramulator.busy_cycles_18_3_0": 800640,
    "ramulator.serving_requests_18_3_0": 811529,
    "ramulator.average_serving_requests_18_3_0": 0.000111,
    "ramulator.active_cycles_18_3_1": 797599,
    "ramulator.busy_cycles_18_3_1": 797599,
    "ramulator.serving_requests_18_3_1": 807083,
    "ramulator.average_serving_requests_18_3_1": 0.00011,
    "ramulator.active_cycles_19": 6337892,
    "ramulator.busy_cycles_19": 156578692,
    "ramulator.serving_requests_19": 6495126,
    "ramulator.average_serving_requests_19": 0.000886,
    "ramulator.active_cycles_19_0": 1602799,
    "ramulator.busy_cycles_19_0": 1602799,
    "ramulator.serving_requests_19_0": 1623385,
    "ramulator.average_serving_requests_19_0": 0.000221,
    "ramulator.active_cycles_19_0_0": 800534,
    "ramulator.busy_cycles_19_0_0": 800534,
    "ramulator.serving_requests_19_0_0": 809685,
    "ramulator.average_serving_requests_19_0_0": 0.00011,
    "ramulator.active_cycles_19_0_1": 803696,
    "ramulator.busy_cycles_19_0_1": 803696,
    "ramulator.serving_requests_19_0_1": 813700,
    "ramulator.average_serving_requests_19_0_1": 0.000111,
    "ramulator.active_cycles_19_1": 1606003,
    "ramulator.busy_cycles_19_1": 1606003,
    "ramulator.serving_requests_19_1": 1628697,
    "ramulator.average_serving_requests_19_1": 0.000222,
    "ramulator.active_cycles_19_1_0": 803706,
    "ramulator.busy_cycles_19_1_0": 803706,
    "ramulator.serving_requests_19_1_0": 814190,
    "ramulator.average_serving_requests_19_1_0": 0.000111,
    "ramulator.active_cycles_19_1_1": 803678,
    "ramulator.busy_cycles_19_1_1": 803678,
    "ramulator.serving_requests_19_1_1": 814507,
    "ramulator.average_serving_requests_19_1_1": 0.000111,
    "ramulator.active_cycles_19_2": 1596105,
    "ramulator.busy_cycles_19_2": 1596105,
    "ramulator.serving_requests_19_2": 1616017,
    "ramulator.average_serving_requests_19_2": 0.00022,
    "ramulator.active_cycles_19_2_0": 802775,
    "ramulator.busy_cycles_19_2_0": 802775,
    "ramulator.serving_requests_19_2_0": 811953,
    "ramulator.average_serving_requests_19_2_0": 0.000111,
    "ramulator.active_cycles_19_2_1": 794195,
    "ramulator.busy_cycles_19_2_1": 794195,
    "ramulator.serving_requests_19_2_1": 804064,
    "ramulator.average_serving_requests_19_2_1": 0.00011,
    "ramulator.active_cycles_19_3": 1604402,
    "ramulator.busy_cycles_19_3": 1604402,
    "ramulator.serving_requests_19_3": 1627027,
    "ramulator.average_serving_requests_19_3": 0.000222,
    "ramulator.active_cycles_19_3_0": 808295,
    "ramulator.busy_cycles_19_3_0": 808295,
    "ramulator.serving_requests_19_3_0": 819496,
    "ramulator.average_serving_requests_19_3_0": 0.000112,
    "ramulator.active_cycles_19_3_1": 797769,
    "ramulator.busy_cycles_19_3_1": 797769,
    "ramulator.serving_requests_19_3_1": 807531,
    "ramulator.average_serving_requests_19_3_1": 0.00011,
    "ramulator.active_cycles_20": 6338292,
    "ramulator.busy_cycles_20": 156581492,
    "ramulator.serving_requests_20": 6491308,
    "ramulator.average_serving_requests_20": 0.000886,
    "ramulator.active_cycles_20_0": 1607431,
    "ramulator.busy_cycles_20_0": 1607431,
    "ramulator.serving_requests_20_0": 1627329,
    "ramulator.average_serving_requests_20_0": 0.000222,
    "ramulator.active_cycles_20_0_0": 803145,
    "ramulator.busy_cycles_20_0_0": 803145,
    "ramulator.serving_requests_20_0_0": 812030,
    "ramulator.average_serving_requests_20_0_0": 0.000111,
    "ramulator.active_cycles_20_0_1": 805096,
    "ramulator.busy_cycles_20_0_1": 805096,
    "ramulator.serving_requests_20_0_1": 815299,
    "ramulator.average_serving_requests_20_0_1": 0.000111,
    "ramulator.active_cycles_20_1": 1603407,
    "ramulator.busy_cycles_20_1": 1603407,
    "ramulator.serving_requests_20_1": 1625600,
    "ramulator.average_serving_requests_20_1": 0.000222,
    "ramulator.active_cycles_20_1_0": 804056,
    "ramulator.busy_cycles_20_1_0": 804056,
    "ramulator.serving_requests_20_1_0": 815082,
    "ramulator.average_serving_requests_20_1_0": 0.000111,
    "ramulator.active_cycles_20_1_1": 800265,
    "ramulator.busy_cycles_20_1_1": 800265,
    "ramulator.serving_requests_20_1_1": 810518,
    "ramulator.average_serving_requests_20_1_1": 0.000111,
    "ramulator.active_cycles_20_2": 1590843,
    "ramulator.busy_cycles_20_2": 1590843,
    "ramulator.serving_requests_20_2": 1611251,
    "ramulator.average_serving_requests_20_2": 0.00022,
    "ramulator.active_cycles_20_2_0": 796728,
    "ramulator.busy_cycles_20_2_0": 796728,
    "ramulator.serving_requests_20_2_0": 805806,
    "ramulator.average_serving_requests_20_2_0": 0.00011,
    "ramulator.active_cycles_20_2_1": 795637,
    "ramulator.busy_cycles_20_2_1": 795637,
    "ramulator.serving_requests_20_2_1": 805445,
    "ramulator.average_serving_requests_20_2_1": 0.00011,
    "ramulator.active_cycles_20_3": 1604386,
    "ramulator.busy_cycles_20_3": 1604386,
    "ramulator.serving_requests_20_3": 1627128,
    "ramulator.average_serving_requests_20_3": 0.000222,
    "ramulator.active_cycles_20_3_0": 802892,
    "ramulator.busy_cycles_20_3_0": 802892,
    "ramulator.serving_requests_20_3_0": 813139,
    "ramulator.average_serving_requests_20_3_0": 0.000111,
    "ramulator.active_cycles_20_3_1": 803321,
    "ramulator.busy_cycles_20_3_1": 803321,
    "ramulator.serving_requests_20_3_1": 813989,
    "ramulator.average_serving_requests_20_3_1": 0.000111,
    "ramulator.active_cycles_21": 6338734,
    "ramulator.busy_cycles_21": 156579334,
    "ramulator.serving_requests_21": 6509715,
    "ramulator.average_serving_requests_21": 0.000888,
    "ramulator.active_cycles_21_0": 1613250,
    "ramulator.busy_cycles_21_0": 1613250,
    "ramulator.serving_requests_21_0": 1632623,
    "ramulator.average_serving_requests_21_0": 0.000223,
    "ramulator.active_cycles_21_0_0": 807891,
    "ramulator.busy_cycles_21_0_0": 807891,
    "ramulator.serving_requests_21_0_0": 817354,
    "ramulator.average_serving_requests_21_0_0": 0.000112,
    "ramulator.active_cycles_21_0_1": 806237,
    "ramulator.busy_cycles_21_0_1": 806237,
    "ramulator.serving_requests_21_0_1": 815269,
    "ramulator.average_serving_requests_21_0_1": 0.000111,
    "ramulator.active_cycles_21_1": 1605884,
    "ramulator.busy_cycles_21_1": 1605884,
    "ramulator.serving_requests_21_1": 1628236,
    "ramulator.average_serving_requests_21_1": 0.000222,
    "ramulator.active_cycles_21_1_0": 800934,
    "ramulator.busy_cycles_21_1_0": 800934,
    "ramulator.serving_requests_21_1_0": 811958,
    "ramulator.average_serving_requests_21_1_0": 0.000111,
    "ramulator.active_cycles_21_1_1": 805653,
    "ramulator.busy_cycles_21_1_1": 805653,
    "ramulator.serving_requests_21_1_1": 816278,
    "ramulator.average_serving_requests_21_1_1": 0.000111,
    "ramulator.active_cycles_21_2": 1604605,
    "ramulator.busy_cycles_21_2": 1604605,
    "ramulator.serving_requests_21_2": 1625063,
    "ramulator.average_serving_requests_21_2": 0.000222,
    "ramulator.active_cycles_21_2_0": 803661,
    "ramulator.busy_cycles_21_2_0": 803661,
    "ramulator.serving_requests_21_2_0": 812047,
    "ramulator.average_serving_requests_21_2_0": 0.000111,
    "ramulator.active_cycles_21_2_1": 802464,
    "ramulator.busy_cycles_21_2_1": 802464,
    "ramulator.serving_requests_21_2_1": 813016,
    "ramulator.average_serving_requests_21_2_1": 0.000111,
    "ramulator.active_cycles_21_3": 1601577,
    "ramulator.busy_cycles_21_3": 1601577,
    "ramulator.serving_requests_21_3": 1623793,
    "ramulator.average_serving_requests_21_3": 0.000222,
    "ramulator.active_cycles_21_3_0": 802331,
    "ramulator.busy_cycles_21_3_0": 802331,
    "ramulator.serving_requests_21_3_0": 811790,
    "ramulator.average_serving_requests_21_3_0": 0.000111,
    "ramulator.active_cycles_21_3_1": 801721,
    "ramulator.busy_cycles_21_3_1": 801721,
    "ramulator.serving_requests_21_3_1": 812003,
    "ramulator.average_serving_requests_21_3_1": 0.000111,
    "ramulator.active_cycles_22": 6333243,
    "ramulator.busy_cycles_22": 156574643,
    "ramulator.serving_requests_22": 6490141,
    "ramulator.average_serving_requests_22": 0.000885,
    "ramulator.active_cycles_22_0": 1607696,
    "ramulator.busy_cycles_22_0": 1607696,
    "ramulator.serving_requests_22_0": 1627958,
    "ramulator.average_serving_requests_22_0": 0.000222,
    "ramulator.active_cycles_22_0_0": 809601,
    "ramulator.busy_cycles_22_0_0": 809601,
    "ramulator.serving_requests_22_0_0": 819626,
    "ramulator.average_serving_requests_22_0_0": 0.000112,
    "ramulator.active_cycles_22_0_1": 799435,
    "ramulator.busy_cycles_22_0_1": 799435,
    "ramulator.serving_requests_22_0_1": 808332,
    "ramulator.average_serving_requests_22_0_1": 0.00011,
    "ramulator.active_cycles_22_1": 1606637,
    "ramulator.busy_cycles_22_1": 1606637,
    "ramulator.serving_requests_22_1": 1630005,
    "ramulator.average_serving_requests_22_1": 0.000222,
    "ramulator.active_cycles_22_1_0": 801790,
    "ramulator.busy_cycles_22_1_0": 801790,
    "ramulator.serving_requests_22_1_0": 813042,
    "ramulator.average_serving_requests_22_1_0": 0.000111,
    "ramulator.active_cycles_22_1_1": 805889,
    "ramulator.busy_cycles_22_1_1": 805889,
    "ramulator.serving_requests_22_1_1": 816963,
    "ramulator.average_serving_requests_22_1_1": 0.000111,
    "ramulator.active_cycles_22_2": 1591766,
    "ramulator.busy_cycles_22_2": 1591766,
    "ramulator.serving_requests_22_2": 1610928,
    "ramulator.average_serving_requests_22_2": 0.00022,
    "ramulator.active_cycles_22_2_0": 795924,
    "ramulator.busy_cycles_22_2_0": 795924,
    "ramulator.serving_requests_22_2_0": 804291,
    "ramulator.average_serving_requests_22_2_0": 0.00011,
    "ramulator.active_cycles_22_2_1": 797172,
    "ramulator.busy_cycles_22_2_1": 797172,
    "ramulator.serving_requests_22_2_1": 806637,
    "ramulator.average_serving_requests_22_2_1": 0.00011,
    "ramulator.active_cycles_22_3": 1597978,
    "ramulator.busy_cycles_22_3": 1597978,
    "ramulator.serving_requests_22_3": 1621250,
    "ramulator.average_serving_requests_22_3": 0.000221,
    "ramulator.active_cycles_22_3_0": 800184,
    "ramulator.busy_cycles_22_3_0": 800184,
    "ramulator.serving_requests_22_3_0": 810130,
    "ramulator.average_serving_requests_22_3_0": 0.000111,
    "ramulator.active_cycles_22_3_1": 800116,
    "ramulator.busy_cycles_22_3_1": 800116,
    "ramulator.serving_requests_22_3_1": 811120,
    "ramulator.average_serving_requests_22_3_1": 0.000111,
    "ramulator.active_cycles_23": 6340096,
    "ramulator.busy_cycles_23": 156572896,
    "ramulator.serving_requests_23": 6497188,
    "ramulator.average_serving_requests_23": 0.000886,
    "ramulator.active_cycles_23_0": 1611057,
    "ramulator.busy_cycles_23_0": 1611057,
    "ramulator.serving_requests_23_0": 1631787,
    "ramulator.average_serving_requests_23_0": 0.000223,
    "ramulator.active_cycles_23_0_0": 810031,
    "ramulator.busy_cycles_23_0_0": 810031,
    "ramulator.serving_requests_23_0_0": 819906,
    "ramulator.average_serving_requests_23_0_0": 0.000112,
    "ramulator.active_cycles_23_0_1": 802475,
    "ramulator.busy_cycles_23_0_1": 802475,
    "ramulator.serving_requests_23_0_1": 811881,
    "ramulator.average_serving_requests_23_0_1": 0.000111,
    "ramulator.active_cycles_23_1": 1612317,
    "ramulator.busy_cycles_23_1": 1612317,
    "ramulator.serving_requests_23_1": 1636405,
    "ramulator.average_serving_requests_23_1": 0.000223,
    "ramulator.active_cycles_23_1_0": 803893,
    "ramulator.busy_cycles_23_1_0": 803893,
    "ramulator.serving_requests_23_1_0": 816052,
    "ramulator.average_serving_requests_23_1_0": 0.000111,
    "ramulator.active_cycles_23_1_1": 809382,
    "ramulator.busy_cycles_23_1_1": 809382,
    "ramulator.serving_requests_23_1_1": 820353,
    "ramulator.average_serving_requests_23_1_1": 0.000112,
    "ramulator.active_cycles_23_2": 1593048,
    "ramulator.busy_cycles_23_2": 1593048,
    "ramulator.serving_requests_23_2": 1613241,
    "ramulator.average_serving_requests_23_2": 0.00022,
    "ramulator.active_cycles_23_2_0": 799950,
    "ramulator.busy_cycles_23_2_0": 799950,
    "ramulator.serving_requests_23_2_0": 808853,
    "ramulator.average_serving_requests_23_2_0": 0.00011,
    "ramulator.active_cycles_23_2_1": 794492,
    "ramulator.busy_cycles_23_2_1": 794492,
    "ramulator.serving_requests_23_2_1": 804388,
    "ramulator.average_serving_requests_23_2_1": 0.00011,
    "ramulator.active_cycles_23_3": 1593475,
    "ramulator.busy_cycles_23_3": 1593475,
    "ramulator.serving_requests_23_3": 1615755,
    "ramulator.average_serving_requests_23_3": 0.00022,
    "ramulator.active_cycles_23_3_0": 799735,
    "ramulator.busy_cycles_23_3_0": 799735,
    "ramulator.serving_requests_23_3_0": 809215,
    "ramulator.average_serving_requests_23_3_0": 0.00011,
    "ramulator.active_cycles_23_3_1": 795820,
    "ramulator.busy_cycles_23_3_1": 795820,
    "ramulator.serving_requests_23_3_1": 806540,
    "ramulator.average_serving_requests_23_3_1": 0.00011,
    "ramulator.active_cycles_24": 6329673,
    "ramulator.busy_cycles_24": 156572473,
    "ramulator.serving_requests_24": 6486443,
    "ramulator.average_serving_requests_24": 0.000885,
    "ramulator.active_cycles_24_0": 1607768,
    "ramulator.busy_cycles_24_0": 1607768,
    "ramulator.serving_requests_24_0": 1629207,
    "ramulator.average_serving_requests_24_0": 0.000222,
    "ramulator.active_cycles_24_0_0": 805445,
    "ramulator.busy_cycles_24_0_0": 805445,
    "ramulator.serving_requests_24_0_0": 815452,
    "ramulator.average_serving_requests_24_0_0": 0.000111,
    "ramulator.active_cycles_24_0_1": 803961,
    "ramulator.busy_cycles_24_0_1": 803961,
    "ramulator.serving_requests_24_0_1": 813755,
    "ramulator.average_serving_requests_24_0_1": 0.000111,
    "ramulator.active_cycles_24_1": 1603654,
    "ramulator.busy_cycles_24_1": 1603654,
    "ramulator.serving_requests_24_1": 1625708,
    "ramulator.average_serving_requests_24_1": 0.000222,
    "ramulator.active_cycles_24_1_0": 803084,
    "ramulator.busy_cycles_24_1_0": 803084,
    "ramulator.serving_requests_24_1_0": 813805,
    "ramulator.average_serving_requests_24_1_0": 0.000111,
    "ramulator.active_cycles_24_1_1": 800865,
    "ramulator.busy_cycles_24_1_1": 800865,
    "ramulator.serving_requests_24_1_1": 811903,
    "ramulator.average_serving_requests_24_1_1": 0.000111,
    "ramulator.active_cycles_24_2": 1599156,
    "ramulator.busy_cycles_24_2": 1599156,
    "ramulator.serving_requests_24_2": 1618733,
    "ramulator.average_serving_requests_24_2": 0.000221,
    "ramulator.active_cycles_24_2_0": 804378,
    "ramulator.busy_cycles_24_2_0": 804378,
    "ramulator.serving_requests_24_2_0": 813043,
    "ramulator.average_serving_requests_24_2_0": 0.000111,
    "ramulator.active_cycles_24_2_1": 796305,
    "ramulator.busy_cycles_24_2_1": 796305,
    "ramulator.serving_requests_24_2_1": 805690,
    "ramulator.average_serving_requests_24_2_1": 0.00011,
    "ramulator.active_cycles_24_3": 1592597,
    "ramulator.busy_cycles_24_3": 1592597,
    "ramulator.serving_requests_24_3": 1612795,
    "ramulator.average_serving_requests_24_3": 0.00022,
    "ramulator.active_cycles_24_3_0": 796950,
    "ramulator.busy_cycles_24_3_0": 796950,
    "ramulator.serving_requests_24_3_0": 806205,
    "ramulator.average_serving_requests_24_3_0": 0.00011,
    "ramulator.active_cycles_24_3_1": 797498,
    "ramulator.busy_cycles_24_3_1": 797498,
    "ramulator.serving_requests_24_3_1": 806590,
    "ramulator.average_serving_requests_24_3_1": 0.00011,
    "ramulator.active_cycles_25": 6321281,
    "ramulator.busy_cycles_25": 156569881,
    "ramulator.serving_requests_25": 6491684,
    "ramulator.average_serving_requests_25": 0.000886,
    "ramulator.active_cycles_25_0": 1608863,
    "ramulator.busy_cycles_25_0": 1608863,
    "ramulator.serving_requests_25_0": 1630428,
    "ramulator.average_serving_requests_25_0": 0.000222,
    "ramulator.active_cycles_25_0_0": 805831,
    "ramulator.busy_cycles_25_0_0": 805831,
    "ramulator.serving_requests_25_0_0": 815850,
    "ramulator.average_serving_requests_25_0_0": 0.000111,
    "ramulator.active_cycles_25_0_1": 804670,
    "ramulator.busy_cycles_25_0_1": 804670,
    "ramulator.serving_requests_25_0_1": 814578,
    "ramulator.average_serving_requests_25_0_1": 0.000111,
    "ramulator.active_cycles_25_1": 1604659,
    "ramulator.busy_cycles_25_1": 1604659,
    "ramulator.serving_requests_25_1": 1625458,
    "ramulator.average_serving_requests_25_1": 0.000222,
    "ramulator.active_cycles_25_1_0": 803671,
    "ramulator.busy_cycles_25_1_0": 803671,
    "ramulator.serving_requests_25_1_0": 813077,
    "ramulator.average_serving_requests_25_1_0": 0.000111,
    "ramulator.active_cycles_25_1_1": 801774,
    "ramulator.busy_cycles_25_1_1": 801774,
    "ramulator.serving_requests_25_1_1": 812381,
    "ramulator.average_serving_requests_25_1_1": 0.000111,
    "ramulator.active_cycles_25_2": 1595214,
    "ramulator.busy_cycles_25_2": 1595214,
    "ramulator.serving_requests_25_2": 1616154,
    "ramulator.average_serving_requests_25_2": 0.00022,
    "ramulator.active_cycles_25_2_0": 800412,
    "ramulator.busy_cycles_25_2_0": 800412,
    "ramulator.serving_requests_25_2_0": 809959,
    "ramulator.average_serving_requests_25_2_0": 0.00011,
    "ramulator.active_cycles_25_2_1": 796706,
    "ramulator.busy_cycles_25_2_1": 796706,
    "ramulator.serving_requests_25_2_1": 806195,
    "ramulator.average_serving_requests_25_2_1": 0.00011,
    "ramulator.active_cycles_25_3": 1599107,
    "ramulator.busy_cycles_25_3": 1599107,
    "ramulator.serving_requests_25_3": 1619644,
    "ramulator.average_serving_requests_25_3": 0.000221,
    "ramulator.active_cycles_25_3_0": 801528,
    "ramulator.busy_cycles_25_3_0": 801528,
    "ramulator.serving_requests_25_3_0": 810851,
    "ramulator.average_serving_requests_25_3_0": 0.000111,
    "ramulator.active_cycles_25_3_1": 799427,
    "ramulator.busy_cycles_25_3_1": 799427,
    "ramulator.serving_requests_25_3_1": 808793,
    "ramulator.average_serving_requests_25_3_1": 0.00011,
    "ramulator.active_cycles_26": 6323734,
    "ramulator.busy_cycles_26": 156567734,
    "ramulator.serving_requests_26": 6481193,
    "ramulator.average_serving_requests_26": 0.000884,
    "ramulator.active_cycles_26_0": 1602967,
    "ramulator.busy_cycles_26_0": 1602967,
    "ramulator.serving_requests_26_0": 1623784,
    "ramulator.average_serving_requests_26_0": 0.000222,
    "ramulator.active_cycles_26_0_0": 803149,
    "ramulator.busy_cycles_26_0_0": 803149,
    "ramulator.serving_requests_26_0_0": 812577,
    "ramulator.average_serving_requests_26_0_0": 0.000111,
    "ramulator.active_cycles_26_0_1": 801436,
    "ramulator.busy_cycles_26_0_1": 801436,
    "ramulator.serving_requests_26_0_1": 811207,
    "ramulator.average_serving_requests_26_0_1": 0.000111,
    "ramulator.active_cycles_26_1": 1599061,
    "ramulator.busy_cycles_26_1": 1599061,
    "ramulator.serving_requests_26_1": 1622359,
    "ramulator.average_serving_requests_26_1": 0.000221,
    "ramulator.active_cycles_26_1_0": 802182,
    "ramulator.busy_cycles_26_1_0": 802182,
    "ramulator.serving_requests_26_1_0": 812679,
    "ramulator.average_serving_requests_26_1_0": 0.000111,
    "ramulator.active_cycles_26_1_1": 798001,
    "ramulator.busy_cycles_26_1_1": 798001,
    "ramulator.serving_requests_26_1_1": 809680,
    "ramulator.average_serving_requests_26_1_1": 0.00011,
    "ramulator.active_cycles_26_2": 1599942,
    "ramulator.busy_cycles_26_2": 1599942,
    "ramulator.serving_requests_26_2": 1621880,
    "ramulator.average_serving_requests_26_2": 0.000221,
    "ramulator.active_cycles_26_2_0": 802235,
    "ramulator.busy_cycles_26_2_0": 802235,
    "ramulator.serving_requests_26_2_0": 812671,
    "ramulator.average_serving_requests_26_2_0": 0.000111,
    "ramulator.active_cycles_26_2_1": 799917,
    "ramulator.busy_cycles_26_2_1": 799917,
    "ramulator.serving_requests_26_2_1": 809209,
    "ramulator.average_serving_requests_26_2_1": 0.00011,
    "ramulator.active_cycles_26_3": 1592800,
    "ramulator.busy_cycles_26_3": 1592800,
    "ramulator.serving_requests_26_3": 1613170,
    "ramulator.average_serving_requests_26_3": 0.00022,
    "ramulator.active_cycles_26_3_0": 797273,
    "ramulator.busy_cycles_26_3_0": 797273,
    "ramulator.serving_requests_26_3_0": 806058,
    "ramulator.average_serving_requests_26_3_0": 0.00011,
    "ramulator.active_cycles_26_3_1": 797837,
    "ramulator.busy_cycles_26_3_1": 797837,
    "ramulator.serving_requests_26_3_1": 807112,
    "ramulator.average_serving_requests_26_3_1": 0.00011,
    "ramulator.active_cycles_27": 6327943,
    "ramulator.busy_cycles_27": 156568343,
    "ramulator.serving_requests_27": 6486518,
    "ramulator.average_serving_requests_27": 0.000885,
    "ramulator.active_cycles_27_0": 1599731,
    "ramulator.busy_cycles_27_0": 1599731,
    "ramulator.serving_requests_27_0": 1620317,
    "ramulator.average_serving_requests_27_0": 0.000221,
    "ramulator.active_cycles_27_0_0": 795268,
    "ramulator.busy_cycles_27_0_0": 795268,
    "ramulator.serving_requests_27_0_0": 804641,
    "ramulator.average_serving_requests_27_0_0": 0.00011,
    "ramulator.active_cycles_27_0_1": 805887,
    "ramulator.busy_cycles_27_0_1": 805887,
    "ramulator.serving_requests_27_0_1": 815676,
    "ramulator.average_serving_requests_27_0_1": 0.000111,
    "ramulator.active_cycles_27_1": 1599595,
    "ramulator.busy_cycles_27_1": 1599595,
    "ramulator.serving_requests_27_1": 1621721,
    "ramulator.average_serving_requests_27_1": 0.000221,
    "ramulator.active_cycles_27_1_0": 802200,
    "ramulator.busy_cycles_27_1_0": 802200,
    "ramulator.serving_requests_27_1_0": 812585,
    "ramulator.average_serving_requests_27_1_0": 0.000111,
    "ramulator.active_cycles_27_1_1": 798532,
    "ramulator.busy_cycles_27_1_1": 798532,
    "ramulator.serving_requests_27_1_1": 809136,
    "ramulator.average_serving_requests_27_1_1": 0.00011,
    "ramulator.active_cycles_27_2": 1602242,
    "ramulator.busy_cycles_27_2": 1602242,
    "ramulator.serving_requests_27_2": 1622988,
    "ramulator.average_serving_requests_27_2": 0.000221,
    "ramulator.active_cycles_27_2_0": 804700,
    "ramulator.busy_cycles_27_2_0": 804700,
    "ramulator.serving_requests_27_2_0": 814123,
    "ramulator.average_serving_requests_27_2_0": 0.000111,
    "ramulator.active_cycles_27_2_1": 799785,
    "ramulator.busy_cycles_27_2_1": 799785,
    "ramulator.serving_requests_27_2_1": 808865,
    "ramulator.average_serving_requests_27_2_1": 0.00011,
    "ramulator.active_cycles_27_3": 1601348,
    "ramulator.busy_cycles_27_3": 1601348,
    "ramulator.serving_requests_27_3": 1621492,
    "ramulator.average_serving_requests_27_3": 0.000221,
    "ramulator.active_cycles_27_3_0": 800079,
    "ramulator.busy_cycles_27_3_0": 800079,
    "ramulator.serving_requests_27_3_0": 808606,
    "ramulator.average_serving_requests_27_3_0": 0.00011,
    "ramulator.active_cycles_27_3_1": 803717,
    "ramulator.busy_cycles_27_3_1": 803717,
    "ramulator.serving_requests_27_3_1": 812886,
    "ramulator.average_serving_requests_27_3_1": 0.000111,
    "ramulator.active_cycles_28": 6319389,
    "ramulator.busy_cycles_28": 156562589,
    "ramulator.serving_requests_28": 6480661,
    "ramulator.average_serving_requests_28": 0.000884,
    "ramulator.active_cycles_28_0": 1604751,
    "ramulator.busy_cycles_28_0": 1604751,
    "ramulator.serving_requests_28_0": 1624614,
    "ramulator.average_serving_requests_28_0": 0.000222,
    "ramulator.active_cycles_28_0_0": 802777,
    "ramulator.busy_cycles_28_0_0": 802777,
    "ramulator.serving_requests_28_0_0": 811868,
    "ramulator.average_serving_requests_28_0_0": 0.000111,
    "ramulator.active_cycles_28_0_1": 803138,
    "ramulator.busy_cycles_28_0_1": 803138,
    "ramulator.serving_requests_28_0_1": 812746,
    "ramulator.average_serving_requests_28_0_1": 0.000111,
    "ramulator.active_cycles_28_1": 1603284,
    "ramulator.busy_cycles_28_1": 1603284,
    "ramulator.serving_requests_28_1": 1624654,
    "ramulator.average_serving_requests_28_1": 0.000222,
    "ramulator.active_cycles_28_1_0": 801621,
    "ramulator.busy_cycles_28_1_0": 801621,
    "ramulator.serving_requests_28_1_0": 811828,
    "ramulator.average_serving_requests_28_1_0": 0.000111,
    "ramulator.active_cycles_28_1_1": 803348,
    "ramulator.busy_cycles_28_1_1": 803348,
    "ramulator.serving_requests_28_1_1": 812826,
    "ramulator.average_serving_requests_28_1_1": 0.000111,
    "ramulator.active_cycles_28_2": 1593921,
    "ramulator.busy_cycles_28_2": 1593921,
    "ramulator.serving_requests_28_2": 1616622,
    "ramulator.average_serving_requests_28_2": 0.000221,
    "ramulator.active_cycles_28_2_0": 798921,
    "ramulator.busy_cycles_28_2_0": 798921,
    "ramulator.serving_requests_28_2_0": 807521,
    "ramulator.average_serving_requests_28_2_0": 0.00011,
    "ramulator.active_cycles_28_2_1": 797421,
    "ramulator.busy_cycles_28_2_1": 797421,
    "ramulator.serving_requests_28_2_1": 809101,
    "ramulator.average_serving_requests_28_2_1": 0.00011,
    "ramulator.active_cycles_28_3": 1593989,
    "ramulator.busy_cycles_28_3": 1593989,
    "ramulator.serving_requests_28_3": 1614771,
    "ramulator.average_serving_requests_28_3": 0.00022,
    "ramulator.active_cycles_28_3_0": 800717,
    "ramulator.busy_cycles_28_3_0": 800717,
    "ramulator.serving_requests_28_3_0": 810903,
    "ramulator.average_serving_requests_28_3_0": 0.000111,
    "ramulator.active_cycles_28_3_1": 794408,
    "ramulator.busy_cycles_28_3_1": 794408,
    "ramulator.serving_requests_28_3_1": 803868,
    "ramulator.average_serving_requests_28_3_1": 0.00011,
    "ramulator.active_cycles_29": 6318854,
    "ramulator.busy_cycles_29": 156563054,
    "ramulator.serving_requests_29": 6497954,
    "ramulator.average_serving_requests_29": 0.000886,
    "ramulator.active_cycles_29_0": 1606353,
    "ramulator.busy_cycles_29_0": 1606353,
    "ramulator.serving_requests_29_0": 1626827,
    "ramulator.average_serving_requests_29_0": 0.000222,
    "ramulator.active_cycles_29_0_0": 804959,
    "ramulator.busy_cycles_29_0_0": 804959,
    "ramulator.serving_requests_29_0_0": 814015,
    "ramulator.average_serving_requests_29_0_0": 0.000111,
    "ramulator.active_cycles_29_0_1": 802970,
    "ramulator.busy_cycles_29_0_1": 802970,
    "ramulator.serving_requests_29_0_1": 812812,
    "ramulator.average_serving_requests_29_0_1": 0.000111,
    "ramulator.active_cycles_29_1": 1608779,
    "ramulator.busy_cycles_29_1": 1608779,
    "ramulator.serving_requests_29_1": 1631449,
    "ramulator.average_serving_requests_29_1": 0.000223,
    "ramulator.active_cycles_29_1_0": 809796,
    "ramulator.busy_cycles_29_1_0": 809796,
    "ramulator.serving_requests_29_1_0": 819868,
    "ramulator.average_serving_requests_29_1_0": 0.000112,
    "ramulator.active_cycles_29_1_1": 801419,
    "ramulator.busy_cycles_29_1_1": 801419,
    "ramulator.serving_requests_29_1_1": 811581,
    "ramulator.average_serving_requests_29_1_1": 0.000111,
    "ramulator.active_cycles_29_2": 1596531,
    "ramulator.busy_cycles_29_2": 1596531,
    "ramulator.serving_requests_29_2": 1616715,
    "ramulator.average_serving_requests_29_2": 0.000221,
    "ramulator.active_cycles_29_2_0": 799807,
    "ramulator.busy_cycles_29_2_0": 799807,
    "ramulator.serving_requests_29_2_0": 808840,
    "ramulator.average_serving_requests_29_2_0": 0.00011,
    "ramulator.active_cycles_29_2_1": 797979,
    "ramulator.busy_cycles_29_2_1": 797979,
    "ramulator.serving_requests_29_2_1": 807875,
    "ramulator.average_serving_requests_29_2_1": 0.00011,
    "ramulator.active_cycles_29_3": 1603090,
    "ramulator.busy_cycles_29_3": 1603090,
    "ramulator.serving_requests_29_3": 1622963,
    "ramulator.average_serving_requests_29_3": 0.000221,
    "ramulator.active_cycles_29_3_0": 802733,
    "ramulator.busy_cycles_29_3_0": 802733,
    "ramulator.serving_requests_29_3_0": 812296,
    "ramulator.average_serving_requests_29_3_0": 0.000111,
    "ramulator.active_cycles_29_3_1": 801635,
    "ramulator.busy_cycles_29_3_1": 801635,
    "ramulator.serving_requests_29_3_1": 810667,
    "ramulator.average_serving_requests_29_3_1": 0.000111,
    "ramulator.active_cycles_30": 6327867,
    "ramulator.busy_cycles_30": 156566467,
    "ramulator.serving_requests_30": 6489656,
    "ramulator.average_serving_requests_30": 0.000885,
    "ramulator.active_cycles_30_0": 1609783,
    "ramulator.busy_cycles_30_0": 1609783,
    "ramulator.serving_requests_30_0": 1631191,
    "ramulator.average_serving_requests_30_0": 0.000223,
    "ramulator.active_cycles_30_0_0": 808460,
    "ramulator.busy_cycles_30_0_0": 808460,
    "ramulator.serving_requests_30_0_0": 818421,
    "ramulator.average_serving_requests_30_0_0": 0.000112,
    "ramulator.active_cycles_30_0_1": 803091,
    "ramulator.busy_cycles_30_0_1": 803091,
    "ramulator.serving_requests_30_0_1": 812770,
    "ramulator.average_serving_requests_30_0_1": 0.000111,
    "ramulator.active_cycles_30_1": 1603983,
    "ramulator.busy_cycles_30_1": 1603983,
    "ramulator.serving_requests_30_1": 1625988,
    "ramulator.average_serving_requests_30_1": 0.000222,
    "ramulator.active_cycles_30_1_0": 805799,
    "ramulator.busy_cycles_30_1_0": 805799,
    "ramulator.serving_requests_30_1_0": 815749,
    "ramulator.average_serving_requests_30_1_0": 0.000111,
    "ramulator.active_cycles_30_1_1": 800516,
    "ramulator.busy_cycles_30_1_1": 800516,
    "ramulator.serving_requests_30_1_1": 810239,
    "ramulator.average_serving_requests_30_1_1": 0.000111,
    "ramulator.active_cycles_30_2": 1592615,
    "ramulator.busy_cycles_30_2": 1592615,
    "ramulator.serving_requests_30_2": 1612367,
    "ramulator.average_serving_requests_30_2": 0.00022,
    "ramulator.active_cycles_30_2_0": 798952,
    "ramulator.busy_cycles_30_2_0": 798952,
    "ramulator.serving_requests_30_2_0": 808188,
    "ramulator.average_serving_requests_30_2_0": 0.00011,
    "ramulator.active_cycles_30_2_1": 795341,
    "ramulator.busy_cycles_30_2_1": 795341,
    "ramulator.serving_requests_30_2_1": 804179,
    "ramulator.average_serving_requests_30_2_1": 0.00011,
    "ramulator.active_cycles_30_3": 1597961,
    "ramulator.busy_cycles_30_3": 1597961,
    "ramulator.serving_requests_30_3": 1620110,
    "ramulator.average_serving_requests_30_3": 0.000221,
    "ramulator.active_cycles_30_3_0": 797526,
    "ramulator.busy_cycles_30_3_0": 797526,
    "ramulator.serving_requests_30_3_0": 807114,
    "ramulator.average_serving_requests_30_3_0": 0.00011,
    "ramulator.active_cycles_30_3_1": 802570,
    "ramulator.busy_cycles_30_3_1": 802570,
    "ramulator.serving_requests_30_3_1": 812996,
    "ramulator.average_serving_requests_30_3_1": 0.000111,
    "ramulator.active_cycles_31": 6324713,
    "ramulator.busy_cycles_31": 156564513,
    "ramulator.serving_requests_31": 6496353,
    "ramulator.average_serving_requests_31": 0.000886,
    "ramulator.active_cycles_31_0": 1605052,
    "ramulator.busy_cycles_31_0": 1605052,
    "ramulator.serving_requests_31_0": 1626697,
    "ramulator.average_serving_requests_31_0": 0.000222,
    "ramulator.active_cycles_31_0_0": 805013,
    "ramulator.busy_cycles_31_0_0": 805013,
    "ramulator.serving_requests_31_0_0": 815595,
    "ramulator.average_serving_requests_31_0_0": 0.000111,
    "ramulator.active_cycles_31_0_1": 801186,
    "ramulator.busy_cycles_31_0_1": 801186,
    "ramulator.serving_requests_31_0_1": 811102,
    "ramulator.average_serving_requests_31_0_1": 0.000111,
    "ramulator.active_cycles_31_1": 1601546,
    "ramulator.busy_cycles_31_1": 1601546,
    "ramulator.serving_requests_31_1": 1624132,
    "ramulator.average_serving_requests_31_1": 0.000222,
    "ramulator.active_cycles_31_1_0": 804854,
    "ramulator.busy_cycles_31_1_0": 804854,
    "ramulator.serving_requests_31_1_0": 814293,
    "ramulator.average_serving_requests_31_1_0": 0.000111,
    "ramulator.active_cycles_31_1_1": 800554,
    "ramulator.busy_cycles_31_1_1": 800554,
    "ramulator.serving_requests_31_1_1": 809839,
    "ramulator.average_serving_requests_31_1_1": 0.00011,
    "ramulator.active_cycles_31_2": 1599733,
    "ramulator.busy_cycles_31_2": 1599733,
    "ramulator.serving_requests_31_2": 1619969,
    "ramulator.average_serving_requests_31_2": 0.000221,
    "ramulator.active_cycles_31_2_0": 807145,
    "ramulator.busy_cycles_31_2_0": 807145,
    "ramulator.serving_requests_31_2_0": 816343,
    "ramulator.average_serving_requests_31_2_0": 0.000111,
    "ramulator.active_cycles_31_2_1": 794234,
    "ramulator.busy_cycles_31_2_1": 794234,
    "ramulator.serving_requests_31_2_1": 803626,
    "ramulator.average_serving_requests_31_2_1": 0.00011,
    "ramulator.active_cycles_31_3": 1602486,
    "ramulator.busy_cycles_31_3": 1602486,
    "ramulator.serving_requests_31_3": 1625555,
    "ramulator.average_serving_requests_31_3": 0.000222,
    "ramulator.active_cycles_31_3_0": 804882,
    "ramulator.busy_cycles_31_3_0": 804882,
    "ramulator.serving_requests_31_3_0": 814897,
    "ramulator.average_serving_requests_31_3_0": 0.000111,
    "ramulator.active_cycles_31_3_1": 800760,
    "ramulator.busy_cycles_31_3_1": 800760,
    "ramulator.serving_requests_31_3_1": 810658,
    "ramulator.average_serving_requests_31_3_1": 0.000111,
    "ramulator.dram_capacity": 4294967296,
    "ramulator.dram_cycles": 7329976000,
    "ramulator.read_requests": 1981736,
    "ramulator.write_requests": 996424,
    "ramulator.ramulator_active_cycles": 139429180,
    "ramulator.memory_footprint": 0,
    "ramulator.incoming_requests_per_channel": 2978160,
    "ramulator.incoming_read_reqs_per_channel": 1981736,
    "ramulator.physical_page_replacement": 0,
    "ramulator.maximum_internal_bandwidth": 640000000000,
    "ramulator.maximum_link_bandwidth": 480000000000,
    "ramulator.read_bandwidth": 86515361,
    "ramulator.write_bandwidth": 43500235,
    "ramulator.read_latency_avg": 84.403643,
    "ramulator.read_latency_ns_avg": 67.522914,
    "ramulator.read_latency_sum": 167265738,
    "ramulator.queueing_latency_avg": 8.057005,
    "ramulator.queueing_latency_ns_avg": 6.445604,
    "ramulator.queueing_latency_sum": 15966856,
    "ramulator.request_packet_latency_avg": 1.195509,
    "ramulator.request_packet_latency_ns_avg": 0.956408,
    "ramulator.request_packet_latency_sum": 2369184,
    "ramulator.response_packet_latency_avg": 1.001173,
    "ramulator.response_packet_latency_ns_avg": 0.800938,
    "ramulator.response_packet_latency_sum": 1984060,
    "ramulator.read_transaction_bytes": 507324416,
    "ramulator.write_transaction_bytes": 255084544,
    "ramulator.row_hits": 1280242,
    "ramulator.row_misses": 1656296,
    "ramulator.row_conflicts": 41622,
    "ramulator.read_row_hits": 882948,
    "ramulator.read_row_misses": 1073796,
    "ramulator.read_row_conflicts": 24992,
    "ramulator.write_row_hits": 397294,
    "ramulator.write_row_misses": 582500,
    "ramulator.write_row_conflicts": 16630,
    "ramulator.req_queue_length_avg": 0.03151,
    "ramulator.req_queue_length_sum": 230969663,
    "ramulator.read_req_queue_length_avg": 0.022769,
    "ramulator.read_req_queue_length_sum": 166899567,
    "ramulator.write_req_queue_length_avg": 0.008741,
    "ramulator.write_req_queue_length_sum": 64070096,
    "ramulator.record_read_hits": 0.0,
    "ramulator.record_read_misses": 0.0,
    "ramulator.record_read_conflicts": 0.0,
    "ramulator.record_write_hits": 0.0,
    "ramulator.record_write_misses": 0.0,
    "ramulator.record_write_conflicts": 0.0
  },
  "channel_distribution": {
    "ramulator.read_requests": {
      "0": 1781279.0,
      "1": 82135.0,
      "2": 55756.0,
      "3": 62566.0
    },
    "ramulator.write_requests": {
      "0": 937705.0,
      "1": 23273.0,
      "2": 19648.0,
      "3": 15798.0
    },
    "ramulator.incoming_requests_per_channel": {
      "0": 93098.0,
      "1": 93091.0,
      "2": 93156.0,
      "3": 93109.0,
      "4": 93118.0,
      "5": 93104.0,
      "6": 93092.0,
      "7": 93116.0,
      "8": 93142.0,
      "9": 93157.0,
      ":": 93134.0,
      ";": 93074.0,
      "<": 93096.0,
      "=": 93124.0,
      ">": 93052.0,
      "?": 92993.0,
      "@": 93065.0,
      "A": 93015.0,
      "B": 93021.0,
      "C": 93094.0,
      "D": 93108.0,
      "E": 93082.0,
      "F": 93089.0,
      "G": 92989.0,
      "H": 93031.0,
      "I": 93046.0,
      "J": 93036.0,
      "K": 93022.0,
      "L": 92945.0,
      "M": 92976.0,
      "N": 92993.0,
      "O": 92992.0
    },
    "ramulator.incoming_read_reqs_per_channel": {
      "0": 61970.0,
      "1": 61967.0,
      "2": 62016.0,
      "3": 61964.0,
      "4": 61983.0,
      "5": 61961.0,
      "6": 61947.0,
      "7": 61955.0,
      "8": 61978.0,
      "9": 61995.0,
      ":": 61974.0,
      ";": 61915.0,
      "<": 61925.0,
      "=": 61939.0,
      ">": 61914.0,
      "?": 61867.0,
      "@": 61938.0,
      "A": 61892.0,
      "B": 61903.0,
      "C": 61956.0,
      "D": 61972.0,
      "E": 61953.0,
      "F": 61937.0,
      "G": 61830.0,
      "H": 61889.0,
      "I": 61910.0,
      "J": 61904.0,
      "K": 61902.0,
      "L": 61833.0,
      "M": 61864.0,
      "N": 61891.0,
      "O": 61892.0
    },
    "ramulator.read_row_hits": {
      "0": 760701.0,
      "1": 50213.0,
      "2": 33991.0,
      "3": 38043.0
    },
    "ramulator.read_row_misses": {
      "0": 998927.0,
      "1": 30879.0,
      "2": 20822.0,
      "3": 23168.0
    },
    "ramulator.read_row_conflicts": {
      "0": 21651.0,
      "1": 1043.0,
      "2": 943.0,
      "3": 1355.0
    },
    "ramulator.write_row_hits": {
      "0": 365983.0,
      "1": 12294.0,
      "2": 10654.0,
      "3": 8363.0
    },
    "ramulator.write_row_misses": {
      "0": 555654.0,
      "1": 10776.0,
      "2": 8840.0,
      "3": 7230.0
    },
    "ramulator.write_row_conflicts": {
      "0": 16068.0,
      "1": 203.0,
      "2": 154.0,
      "3": 205.0
    },
    "ramulator.record_read_hits": {
      "0": 0.0,
      "1": 0.0,
      "2": 0.0,
      "3": 0.0
    },
    "ramulator.record_read_misses": {
      "0": 0.0,
      "1": 0.0,
      "2": 0.0,
      "3": 0.0
    },
    "ramulator.record_read_conflicts": {
      "0": 0.0,
      "1": 0.0,
      "2": 0.0,
      "3": 0.0
    },
    "ramulator.record_write_hits": {
      "0": 0.0,
      "1": 0.0,
      "2": 0.0,
      "3": 0.0
    },
    "ramulator.record_write_misses": {
      "0": 0.0,
      "1": 0.0,
      "2": 0.0,
      "3": 0.0
    },
    "ramulator.record_write_conflicts": {
      "0": 0.0,
      "1": 0.0,
      "2": 0.0,
      "3": 0.0
    }
  }
}